Workbook

Sheet Comparison
A1: Rank | B1: Scooter | C1: Brand | D1: Variant | E1: Fuel | F1: Kerb weight (kg) | G1: Seat height (mm) | H1: Battery (kWh) / Engine (cc) | I1: Peak power (kW) | J1: Claimed range (km) / mileage (kmpl) | K1: Real-world range (km) / mileage (kmpl) | L1: EV consumption incl. losses (Wh/km) | M1: Top speed (km/h) | N1: Boot (L) | O1: Ex-showroom (₹) | P1: On-road Thoothukudi (₹) | Q1: Price basis | R1: Warranty | S1: Thoothukudi dealer | T1: Dealer status | U1: Service rating | V1: Main advantage | W1: Main disadvantage | X1: Overall (stars) | Y1: Overall score /5 | Z1: ₹ per kg | AA1: Real range ÷ kg (EV) | AB1: Power-to-weight (W/kg) | AC1: Weight vs your Pleasure (kg) | AD1: Seat vs your Pleasure (mm) | AE1: Running cost (₹/km)
A2: 1 | B2: Honda Activa 110 | C2: Honda | D2: STD (DLX/H-Smart higher) | E2: Petrol | F2: 105 | G2: 764 | H2: 109.51 | I2: 5.88 | K2: 50 | M2: 85† | N2: 18 | O2: 78866 | P2: 96000 | Q2: Est. (ex-showroom ✅ + TN RTO/insurance est.) | R2: 3 yr std + up to 7 yr ext. (10 yr total) | S2: Pearl Honda, 5&6 Ettayapuram Rd, Melur – 628002 | T2: Listed | U2: ★★★★★ | V2: Benchmark reliability, best resale, 10-yr warranty option | W2: Small 18 L boot; drum brakes; 10-inch rear | X2: ★★★★★ | Y2: 5 | Z2: =IFERROR(P2/F2,"") | AA2: =IF(E2="EV",IFERROR(K2/F2,""),"n/a") | AB2: =IFERROR(VALUE(SUBSTITUTE(I2,"†",""))*1000/F2,"n/a") | AC2: =F2-Assumptions!$B$8 | AD2: =IFERROR(VALUE(SUBSTITUTE(G2,"†",""))-Assumptions!$B$9,"n/a") | AE2: =IF(E2="EV",L2/1000*Assumptions!$B$5,Assumptions!$B$4/K2)
A3: 2 | B3: TVS iQube 2.2 kWh | C3: TVS | D3: 2.2 kWh | E3: EV | F3: 110 | G3: 770 | H3: 2.2 | I3: 4.4 | J3: 94 | K3: 75 | L3: 33 | M3: 75 | N3: ⚠️ check | O3: 111000 | P3: 115968 | Q3: Thoothukudi listing (BikeWale) | R3: Battery/vehicle 3 yr/50k km; ext. to 5 yr/70k | S3: TVS dealers e.g. Nellai Trading Automobile, 16H/1 Palayamkottai Rd – 628008 | T3: Listed – confirm iQube authorisation | U3: ★★★★☆ | V3: Proven EV, biggest local network, quick 0–40 | W3: Price; modest 75 km real range | X3: ★★★★☆ | Y3: 4.5 | Z3: =IFERROR(P3/F3,"") | AA3: =IF(E3="EV",IFERROR(K3/F3,""),"n/a") | AB3: =IFERROR(VALUE(SUBSTITUTE(I3,"†",""))*1000/F3,"n/a") | AC3: =F3-Assumptions!$B$8 | AD3: =IFERROR(VALUE(SUBSTITUTE(G3,"†",""))-Assumptions!$B$9,"n/a") | AE3: =IF(E3="EV",L3/1000*Assumptions!$B$5,Assumptions!$B$4/K3)
A4: 3 | B4: TVS Jupiter 110 | C4: TVS | D4: Drum | E4: Petrol | F4: 105 | G4: 770 | H4: 113.3 | I4: 5.9 | K4: 50 | M4: 85† | N4: 33 | O4: 73400 | P4: 101049 | Q4: Theni (neighbouring) listing used as proxy | R4: 5 yr / 50,000 km | S4: Nellai Trading Automobile / Mizbah Motors (Ettayapuram Main Rd – 628003) | T4: Listed | U4: ★★★★★ | V4: 33 L two-helmet boot, iGO assist, front fuel filler† | W4: Costs more than Pleasure+ | X4: ★★★★☆ | Y4: 4.5 | Z4: =IFERROR(P4/F4,"") | AA4: =IF(E4="EV",IFERROR(K4/F4,""),"n/a") | AB4: =IFERROR(VALUE(SUBSTITUTE(I4,"†",""))*1000/F4,"n/a") | AC4: =F4-Assumptions!$B$8 | AD4: =IFERROR(VALUE(SUBSTITUTE(G4,"†",""))-Assumptions!$B$9,"n/a") | AE4: =IF(E4="EV",L4/1000*Assumptions!$B$5,Assumptions!$B$4/K4)
A5: 4 | B5: Bajaj Chetak C25 | C5: Bajaj | D5: C25 (C2501) | E5: EV | F5: 108 | G5: 763 | H5: 2.5 | I5: 2.2 | J5: 113 | K5: 90 | L5: 31 | M5: 55 | N5: 25 | O5: 91399 | P5: 96500 | Q5: Thoothukudi listing | R5: Battery 3 yr/50k km; ext. to 5 yr/70k | S5: Susee Bajaj, 99-A Ettayapuram Rd – 628001 (Chetak not confirmed) | T5: Dealer/service availability not confirmed (Chetak) | U5: ★★★☆☆ | V5: Cheapest sensible EV, metal body, ~90 km real | W5: 55 km/h cap; Bajaj EV service complaints | X5: ★★★★☆ | Y5: 4 | Z5: =IFERROR(P5/F5,"") | AA5: =IF(E5="EV",IFERROR(K5/F5,""),"n/a") | AB5: =IFERROR(VALUE(SUBSTITUTE(I5,"†",""))*1000/F5,"n/a") | AC5: =F5-Assumptions!$B$8 | AD5: =IFERROR(VALUE(SUBSTITUTE(G5,"†",""))-Assumptions!$B$9,"n/a") | AE5: =IF(E5="EV",L5/1000*Assumptions!$B$5,Assumptions!$B$4/K5)
A6: 5 | B6: Hero Pleasure+ XTEC | C6: Hero | D6: LX (XTEC ZX ₹93,557) | E6: Petrol | F6: 104 | G6: 765 | H6: 110.9 | I6: 5.9 | J6: 52 | K6: 50 | M6: 75 | O6: 69766 | P6: 86556 | Q6: Thoothukudi listing (Bikes24) | R6: Hero std 5 yr† | S6: Arvinth Auto Agency, 3/201 Korampallam – 628101, 93550 29428 | T6: Listed | U6: ★★★★☆ | V6: Cheapest; feels like your Pleasure; LED+Bluetooth (XTEC) | W6: Basic chassis, drum brakes | X6: ★★★★☆ | Y6: 4 | Z6: =IFERROR(P6/F6,"") | AA6: =IF(E6="EV",IFERROR(K6/F6,""),"n/a") | AB6: =IFERROR(VALUE(SUBSTITUTE(I6,"†",""))*1000/F6,"n/a") | AC6: =F6-Assumptions!$B$8 | AD6: =IFERROR(VALUE(SUBSTITUTE(G6,"†",""))-Assumptions!$B$9,"n/a") | AE6: =IF(E6="EV",L6/1000*Assumptions!$B$5,Assumptions!$B$4/K6)
A7: 6 | B7: TVS Orbiter V1 | C7: TVS | D7: V1 1.8 kWh | E7: EV | F7: 101 | G7: 760 | H7: 1.8 | J7: 86 | K7: 70 | L7: 30 | M7: 68 | N7: 34 | O7: 88250 | P7: 97000 | Q7: Est. (ex-showroom ✅ + ins./reg. est.) | R7: 3 yr† (confirm) | S7: TVS dealers (Orbiter listing not confirmed) | T7: Not confirmed | U7: ★★★★☆ | V7: Lightest EV, 34 L boot, 14-inch front† | W7: Small battery; new model | X7: ★★★☆☆ | Y7: 3.5 | Z7: =IFERROR(P7/F7,"") | AA7: =IF(E7="EV",IFERROR(K7/F7,""),"n/a") | AB7: =IFERROR(VALUE(SUBSTITUTE(I7,"†",""))*1000/F7,"n/a") | AC7: =F7-Assumptions!$B$8 | AD7: =IFERROR(VALUE(SUBSTITUTE(G7,"†",""))-Assumptions!$B$9,"n/a") | AE7: =IF(E7="EV",L7/1000*Assumptions!$B$5,Assumptions!$B$4/K7)
A8: 7 | B8: Ather Rizta S | C8: Ather | D8: S 2.9 kWh (or 2.7 kWh LFP) | E8: EV | F8: 119 | G8: 780 | H8: 2.9 | I8: 4.3 | J8: 123 | K8: 105 | L8: 31 | M8: 80† | N8: 34 | O8: 121499 | P8: 128000 | Q8: Est. (Ather site ex-showroom ✅ + ins./reg.) | R8: Battery 5 yr†; Eight70 8-yr option | S8: Ather – Palayamkottai Rd, 7B/7C/7D – 628008 | T8: Listed | U8: ★★★★☆ | V8: Best range, comfort, software | W8: Heaviest (+15 kg) & costliest | X8: ★★★☆☆ | Y8: 3.5 | Z8: =IFERROR(P8/F8,"") | AA8: =IF(E8="EV",IFERROR(K8/F8,""),"n/a") | AB8: =IFERROR(VALUE(SUBSTITUTE(I8,"†",""))*1000/F8,"n/a") | AC8: =F8-Assumptions!$B$8 | AD8: =IFERROR(VALUE(SUBSTITUTE(G8,"†",""))-Assumptions!$B$9,"n/a") | AE8: =IF(E8="EV",L8/1000*Assumptions!$B$5,Assumptions!$B$4/K8)
A9: 8 | B9: Suzuki Access 125 | C9: Suzuki | D9: Standard | E9: Petrol | F9: 103 | G9: 773 | H9: 124 | I9: 6.4 | J9: 45 | K9: 47 | M9: 90 | N9: 24† | O9: 82185 | P9: 93220 | Q9: Thoothukudi listing (low end of range) | R9: Std + extended† (confirm) | S9: Welcome Motors, 99 College Teachers Colony, Korampallam – 628101, 73737 06007 | T9: Listed | U9: ★★★☆☆ | V9: Smooth 125cc, light | W9: Single local outlet; lower mileage | X9: ★★★☆☆ | Y9: 3.5 | Z9: =IFERROR(P9/F9,"") | AA9: =IF(E9="EV",IFERROR(K9/F9,""),"n/a") | AB9: =IFERROR(VALUE(SUBSTITUTE(I9,"†",""))*1000/F9,"n/a") | AC9: =F9-Assumptions!$B$8 | AD9: =IFERROR(VALUE(SUBSTITUTE(G9,"†",""))-Assumptions!$B$9,"n/a") | AE9: =IF(E9="EV",L9/1000*Assumptions!$B$5,Assumptions!$B$4/K9)
A10: 9 | B10: Yamaha Fascino 125 Fi Hybrid | C10: Yamaha | D10: Drum | E10: Petrol | F10: 99 | G10: 790† | H10: 125 | I10: 6.0† | J10: 49 | K10: 52 | M10: 90† | N10: 21† | O10: 81870 | P10: 96344 | Q10: Thoothukudi listing (ZigWheels, 2 Aug 2026) | R10: Confirm at dealer† | S10: Lakhmi Motors, Muthu Mahal, Tiruchendur Rd – 628216, 73737 30152 | T10: Listed | U10: ★★★☆☆ | V10: Lightest petrol (99 kg), frugal hybrid | W10: Taller seat, small boot, cramped pillion | X10: ★★★☆☆ | Y10: 3 | Z10: =IFERROR(P10/F10,"") | AA10: =IF(E10="EV",IFERROR(K10/F10,""),"n/a") | AB10: =IFERROR(VALUE(SUBSTITUTE(I10,"†",""))*1000/F10,"n/a") | AC10: =F10-Assumptions!$B$8 | AD10: =IFERROR(VALUE(SUBSTITUTE(G10,"†",""))-Assumptions!$B$9,"n/a") | AE10: =IF(E10="EV",L10/1000*Assumptions!$B$5,Assumptions!$B$4/K10)
A11: 10 | B11: Hero Vida VX2 Go | C11: Hero Vida | D11: Go 2.2 kWh (removable) | E11: EV | F11: 115 | G11: 777 | H11: 2.2 | I11: 6 | J11: 92† | K11: 68 | L11: 36 | M11: 70 | N11: 33.2 | O11: 99490 | P11: 105000 | Q11: Est. ⚠️ (listing inconsistent: ex ₹99,490 vs on-road ₹91,353) | R11: Battery 5 yr/50k km (ext. 60k) | S11: Arvinth Auto Agency (Hero) – Vida not confirmed | T11: Dealer/service availability not confirmed | U11: ★★☆☆☆ | V11: Removable battery, 5-yr battery warranty | W11: Local Vida service unconfirmed | X11: ★★★☆☆ | Y11: 3 | Z11: =IFERROR(P11/F11,"") | AA11: =IF(E11="EV",IFERROR(K11/F11,""),"n/a") | AB11: =IFERROR(VALUE(SUBSTITUTE(I11,"†",""))*1000/F11,"n/a") | AC11: =F11-Assumptions!$B$8 | AD11: =IFERROR(VALUE(SUBSTITUTE(G11,"†",""))-Assumptions!$B$9,"n/a") | AE11: =IF(E11="EV",L11/1000*Assumptions!$B$5,Assumptions!$B$4/K11)
B13: Notes:
B14: Rank = overall rank across all 10 (see Rankings sheet for separate EV/petrol rankings).
B15: Columns Z–AE are formulas. ₹/kg = On-road ÷ Kerb weight. Range÷kg uses REAL-WORLD range. W/kg = peak power ÷ kerb weight (EV torque is instant, so EVs feel quicker than W/kg suggests).
B16: Baseline: your Hero Honda Pleasure – 104 kg, 765 mm seat, 102 cc / 6.7 bhp, drum/drum brakes.
B17: Real-world EV range: iQube 75 km (TVS), Chetak C25 ~90 km (Autocar), Rizta 2.9 ~105 km (Autocar); Orbiter V1 & Vida = estimates. Petrol mileage: estimates from road tests/owner reports.
B18: Honourable mention (not ranked): Honda QC1 – 89.5 kg, ₹97,274 on-road Thoothukudi listing, 1.5 kWh, ~50 km/h; local sale/service not confirmed.
B19: † = brochure spec not re-verified Oct 2026; ⚠️ = conflicting/unconfirmed; Est. = estimate.

Sheet Assumptions
A1: Assumptions & Inputs (yellow cells = edit these; blue text = hardcoded input)
A3: Input | B3: Value | C3: Source / note
A4: Petrol price, Thoothukudi (₹/L) | B4: 101.45 | C4: Source: Shriram Finance / GoldPriceIndia, 17 Jul 2026 (latest dated figure found). Update to today's pump price.
A5: Electricity marginal rate for EV charging (₹/unit) | B5: 7 | C5: Estimate. TN domestic slabs ₹4.95–₹12.15/unit (TheDiscomBill, Jul 2026). Use 10 if your household is in a high slab.
A6: Ownership period (years) | B6: 5 | C6: Per your request
A7: Days per year | B7: 365
A8: Your Hero Honda Pleasure kerb weight (kg) | B8: 104 | C8: BikeWale Pleasure 2005-2015 spec
A9: Your Pleasure seat height (mm) | B9: 765 | C9: BikeWale Pleasure 2005-2015 spec
A10: Your Pleasure real-world mileage today (kmpl) | B10: 47 | C10: Estimate for a ~10-year-old carburettor 102cc engine (ARAI 63)
A13: Daily-km scenarios
A14: Scenario | B14: km/day
A15: Scenario 1 | B15: 20
A16: Scenario 2 | B16: 30
A17: Scenario 3 | B17: 50
A19: 5-year maintenance & risk estimates (₹, totals over the ownership period) — ESTIMATES, not quotes
A20: Cost item | B20: EV @ S1 | C20: EV @ S2 | D20: EV @ S3 | E20: Petrol @ S1 | F20: Petrol @ S2 | G20: Petrol @ S3 | H20: Basis
A21: Periodic servicing | B21: 5000 | C21: 6000 | D21: 8000 | E21: 10000 | F21: 14000 | G21: 20000 | H21: Petrol: service every ~3,000–4,000 km at ~₹700–1,200; EV: ~₹600–1,600/yr
A22: Consumables (oil, belt, rollers, plug, brake shoes/pads, 12V battery) | B22: 3000 | C22: 4000 | D22: 7000 | E22: 5000 | F22: 7000 | G22: 12000 | H22: Estimate
A23: Insurance renewals (years 2–5) | B23: 8000 | C23: 8000 | D23: 8000 | E23: 8000 | F23: 8000 | G23: 8000 | H23: ~₹2,000/yr OD renewal (TP prepaid 5 yrs at purchase) – estimate
A24: Tyres | B24: 3500 | C24: 7000 | D24: 10500 | E24: 3500 | F24: 7000 | G24: 10500 | H24: ~₹3,500 per pair every ~25–30k km – estimate
A25: EV battery replacement provision (risk-weighted) | B25: 6000 | C25: 15000 | D25: 30000 | E25: 0 | F25: 0 | G25: 0 | H25: S1: buy extended battery warranty; S3: ~50% chance of a ₹50–60k pack by year 5 (EVFY 2026 battery cost guide)
A26: Total other costs | B26: =SUM(B21:B25) | C26: =SUM(C21:C25) | D26: =SUM(D21:D25) | E26: =SUM(E21:E25) | F26: =SUM(F21:F25) | G26: =SUM(G21:G25)
A28: Legend: Yellow fill + blue text = input you can change. Black = formula. Green = link from another sheet. 'Est.' = estimate. '†' = brochure spec not re-verified Oct 2026.
A29: Prices/availability checked 5 Oct 2026. Central PM E-DRIVE subsidy ended 31 Jul 2026. TN EV road tax = 0% until 31 Dec 2027.

Sheet Weight Analysis
A1: Weight-to-price, range-to-weight and power-to-weight (all values linked from Comparison sheet)
A3: Scooter | B3: Fuel | C3: Kerb weight (kg) | D3: On-road (₹) | E3: ₹ per kg | F3: Rank (₹/kg, low=1) | G3: Real range (km) | H3: Range ÷ kg (EV) | I3: Rank (EV range/kg) | J3: Power-to-weight (W/kg) | K3: Rank (W/kg)
A4: =Comparison!B2 | B4: =Comparison!E2 | C4: =Comparison!F2 | D4: =Comparison!P2 | E4: =Comparison!Z2 | F4: =COUNTIF($E$4:$E$13,"<"&E4)+1 | G4: =IF(B4="EV",Comparison!K2,"") | H4: =IF(B4="EV",Comparison!AA2,"") | I4: =IF(B4="EV",COUNTIFS($B$4:$B$13,"EV",$H$4:$H$13,">"&H4)+1,"") | J4: =Comparison!AB2 | K4: =IF(ISNUMBER(J4),COUNTIF($J$4:$J$13,">"&J4)+1,"n/a")
A5: =Comparison!B3 | B5: =Comparison!E3 | C5: =Comparison!F3 | D5: =Comparison!P3 | E5: =Comparison!Z3 | F5: =COUNTIF($E$4:$E$13,"<"&E5)+1 | G5: =IF(B5="EV",Comparison!K3,"") | H5: =IF(B5="EV",Comparison!AA3,"") | I5: =IF(B5="EV",COUNTIFS($B$4:$B$13,"EV",$H$4:$H$13,">"&H5)+1,"") | J5: =Comparison!AB3 | K5: =IF(ISNUMBER(J5),COUNTIF($J$4:$J$13,">"&J5)+1,"n/a")
A6: =Comparison!B4 | B6: =Comparison!E4 | C6: =Comparison!F4 | D6: =Comparison!P4 | E6: =Comparison!Z4 | F6: =COUNTIF($E$4:$E$13,"<"&E6)+1 | G6: =IF(B6="EV",Comparison!K4,"") | H6: =IF(B6="EV",Comparison!AA4,"") | I6: =IF(B6="EV",COUNTIFS($B$4:$B$13,"EV",$H$4:$H$13,">"&H6)+1,"") | J6: =Comparison!AB4 | K6: =IF(ISNUMBER(J6),COUNTIF($J$4:$J$13,">"&J6)+1,"n/a")
A7: =Comparison!B5 | B7: =Comparison!E5 | C7: =Comparison!F5 | D7: =Comparison!P5 | E7: =Comparison!Z5 | F7: =COUNTIF($E$4:$E$13,"<"&E7)+1 | G7: =IF(B7="EV",Comparison!K5,"") | H7: =IF(B7="EV",Comparison!AA5,"") | I7: =IF(B7="EV",COUNTIFS($B$4:$B$13,"EV",$H$4:$H$13,">"&H7)+1,"") | J7: =Comparison!AB5 | K7: =IF(ISNUMBER(J7),COUNTIF($J$4:$J$13,">"&J7)+1,"n/a")
A8: =Comparison!B6 | B8: =Comparison!E6 | C8: =Comparison!F6 | D8: =Comparison!P6 | E8: =Comparison!Z6 | F8: =COUNTIF($E$4:$E$13,"<"&E8)+1 | G8: =IF(B8="EV",Comparison!K6,"") | H8: =IF(B8="EV",Comparison!AA6,"") | I8: =IF(B8="EV",COUNTIFS($B$4:$B$13,"EV",$H$4:$H$13,">"&H8)+1,"") | J8: =Comparison!AB6 | K8: =IF(ISNUMBER(J8),COUNTIF($J$4:$J$13,">"&J8)+1,"n/a")
A9: =Comparison!B7 | B9: =Comparison!E7 | C9: =Comparison!F7 | D9: =Comparison!P7 | E9: =Comparison!Z7 | F9: =COUNTIF($E$4:$E$13,"<"&E9)+1 | G9: =IF(B9="EV",Comparison!K7,"") | H9: =IF(B9="EV",Comparison!AA7,"") | I9: =IF(B9="EV",COUNTIFS($B$4:$B$13,"EV",$H$4:$H$13,">"&H9)+1,"") | J9: =Comparison!AB7 | K9: =IF(ISNUMBER(J9),COUNTIF($J$4:$J$13,">"&J9)+1,"n/a")
A10: =Comparison!B8 | B10: =Comparison!E8 | C10: =Comparison!F8 | D10: =Comparison!P8 | E10: =Comparison!Z8 | F10: =COUNTIF($E$4:$E$13,"<"&E10)+1 | G10: =IF(B10="EV",Comparison!K8,"") | H10: =IF(B10="EV",Comparison!AA8,"") | I10: =IF(B10="EV",COUNTIFS($B$4:$B$13,"EV",$H$4:$H$13,">"&H10)+1,"") | J10: =Comparison!AB8 | K10: =IF(ISNUMBER(J10),COUNTIF($J$4:$J$13,">"&J10)+1,"n/a")
A11: =Comparison!B9 | B11: =Comparison!E9 | C11: =Comparison!F9 | D11: =Comparison!P9 | E11: =Comparison!Z9 | F11: =COUNTIF($E$4:$E$13,"<"&E11)+1 | G11: =IF(B11="EV",Comparison!K9,"") | H11: =IF(B11="EV",Comparison!AA9,"") | I11: =IF(B11="EV",COUNTIFS($B$4:$B$13,"EV",$H$4:$H$13,">"&H11)+1,"") | J11: =Comparison!AB9 | K11: =IF(ISNUMBER(J11),COUNTIF($J$4:$J$13,">"&J11)+1,"n/a")
A12: =Comparison!B10 | B12: =Comparison!E10 | C12: =Comparison!F10 | D12: =Comparison!P10 | E12: =Comparison!Z10 | F12: =COUNTIF($E$4:$E$13,"<"&E12)+1 | G12: =IF(B12="EV",Comparison!K10,"") | H12: =IF(B12="EV",Comparison!AA10,"") | I12: =IF(B12="EV",COUNTIFS($B$4:$B$13,"EV",$H$4:$H$13,">"&H12)+1,"") | J12: =Comparison!AB10 | K12: =IF(ISNUMBER(J12),COUNTIF($J$4:$J$13,">"&J12)+1,"n/a")
A13: =Comparison!B11 | B13: =Comparison!E11 | C13: =Comparison!F11 | D13: =Comparison!P11 | E13: =Comparison!Z11 | F13: =COUNTIF($E$4:$E$13,"<"&E13)+1 | G13: =IF(B13="EV",Comparison!K11,"") | H13: =IF(B13="EV",Comparison!AA11,"") | I13: =IF(B13="EV",COUNTIFS($B$4:$B$13,"EV",$H$4:$H$13,">"&H13)+1,"") | J13: =Comparison!AB11 | K13: =IF(ISNUMBER(J13),COUNTIF($J$4:$J$13,">"&J13)+1,"n/a")
A16: How to read this:
A17: ₹/kg: lower = more scooter per rupee. But for you LOW WEIGHT is the goal, so a light scooter with a high ₹/kg (Fascino, Orbiter) can still be the right buy.
A18: Range ÷ kg: best combination of light weight + real range. Chetak C25 is the best among EVs close to your Pleasure's 104 kg; Rizta scores high but weighs 119 kg.
A19: W/kg: petrol scooters lead on paper, but EV motors give full torque from standstill (iQube 0–40 km/h in 4.2 s). Chetak C25's low figure shows in its 55 km/h cap.
A20: Do NOT rank purely on these ratios – reliability, dealer support in Thoothukudi and comfort matter as much.

Sheet Running Cost
A1: Energy / fuel running cost by scenario (formulas; change inputs on Assumptions sheet)
D2: ="Scenario 1: "&Assumptions!B15&" km/day" | H2: ="Scenario 2: "&Assumptions!B16&" km/day" | L2: ="Scenario 3: "&Assumptions!B17&" km/day"
A3: Scooter | B3: Fuel | C3: Cost per km (₹) | D3: S1 Daily | E3: S1 Monthly | F3: S1 Annual | G3: S1 5-year | H3: S2 Daily | I3: S2 Monthly | J3: S2 Annual | K3: S2 5-year | L3: S3 Daily | M3: S3 Monthly | N3: S3 Annual | O3: S3 5-year
A4: =Comparison!B2 | B4: =Comparison!E2 | C4: =Comparison!AE2 | D4: =$C4*Assumptions!$B$15 | E4: =D4*30 | F4: =D4*Assumptions!$B$7 | G4: =F4*Assumptions!$B$6 | H4: =$C4*Assumptions!$B$16 | I4: =H4*30 | J4: =H4*Assumptions!$B$7 | K4: =J4*Assumptions!$B$6 | L4: =$C4*Assumptions!$B$17 | M4: =L4*30 | N4: =L4*Assumptions!$B$7 | O4: =N4*Assumptions!$B$6
A5: =Comparison!B3 | B5: =Comparison!E3 | C5: =Comparison!AE3 | D5: =$C5*Assumptions!$B$15 | E5: =D5*30 | F5: =D5*Assumptions!$B$7 | G5: =F5*Assumptions!$B$6 | H5: =$C5*Assumptions!$B$16 | I5: =H5*30 | J5: =H5*Assumptions!$B$7 | K5: =J5*Assumptions!$B$6 | L5: =$C5*Assumptions!$B$17 | M5: =L5*30 | N5: =L5*Assumptions!$B$7 | O5: =N5*Assumptions!$B$6
A6: =Comparison!B4 | B6: =Comparison!E4 | C6: =Comparison!AE4 | D6: =$C6*Assumptions!$B$15 | E6: =D6*30 | F6: =D6*Assumptions!$B$7 | G6: =F6*Assumptions!$B$6 | H6: =$C6*Assumptions!$B$16 | I6: =H6*30 | J6: =H6*Assumptions!$B$7 | K6: =J6*Assumptions!$B$6 | L6: =$C6*Assumptions!$B$17 | M6: =L6*30 | N6: =L6*Assumptions!$B$7 | O6: =N6*Assumptions!$B$6
A7: =Comparison!B5 | B7: =Comparison!E5 | C7: =Comparison!AE5 | D7: =$C7*Assumptions!$B$15 | E7: =D7*30 | F7: =D7*Assumptions!$B$7 | G7: =F7*Assumptions!$B$6 | H7: =$C7*Assumptions!$B$16 | I7: =H7*30 | J7: =H7*Assumptions!$B$7 | K7: =J7*Assumptions!$B$6 | L7: =$C7*Assumptions!$B$17 | M7: =L7*30 | N7: =L7*Assumptions!$B$7 | O7: =N7*Assumptions!$B$6
A8: =Comparison!B6 | B8: =Comparison!E6 | C8: =Comparison!AE6 | D8: =$C8*Assumptions!$B$15 | E8: =D8*30 | F8: =D8*Assumptions!$B$7 | G8: =F8*Assumptions!$B$6 | H8: =$C8*Assumptions!$B$16 | I8: =H8*30 | J8: =H8*Assumptions!$B$7 | K8: =J8*Assumptions!$B$6 | L8: =$C8*Assumptions!$B$17 | M8: =L8*30 | N8: =L8*Assumptions!$B$7 | O8: =N8*Assumptions!$B$6
A9: =Comparison!B7 | B9: =Comparison!E7 | C9: =Comparison!AE7 | D9: =$C9*Assumptions!$B$15 | E9: =D9*30 | F9: =D9*Assumptions!$B$7 | G9: =F9*Assumptions!$B$6 | H9: =$C9*Assumptions!$B$16 | I9: =H9*30 | J9: =H9*Assumptions!$B$7 | K9: =J9*Assumptions!$B$6 | L9: =$C9*Assumptions!$B$17 | M9: =L9*30 | N9: =L9*Assumptions!$B$7 | O9: =N9*Assumptions!$B$6
A10: =Comparison!B8 | B10: =Comparison!E8 | C10: =Comparison!AE8 | D10: =$C10*Assumptions!$B$15 | E10: =D10*30 | F10: =D10*Assumptions!$B$7 | G10: =F10*Assumptions!$B$6 | H10: =$C10*Assumptions!$B$16 | I10: =H10*30 | J10: =H10*Assumptions!$B$7 | K10: =J10*Assumptions!$B$6 | L10: =$C10*Assumptions!$B$17 | M10: =L10*30 | N10: =L10*Assumptions!$B$7 | O10: =N10*Assumptions!$B$6
A11: =Comparison!B9 | B11: =Comparison!E9 | C11: =Comparison!AE9 | D11: =$C11*Assumptions!$B$15 | E11: =D11*30 | F11: =D11*Assumptions!$B$7 | G11: =F11*Assumptions!$B$6 | H11: =$C11*Assumptions!$B$16 | I11: =H11*30 | J11: =H11*Assumptions!$B$7 | K11: =J11*Assumptions!$B$6 | L11: =$C11*Assumptions!$B$17 | M11: =L11*30 | N11: =L11*Assumptions!$B$7 | O11: =N11*Assumptions!$B$6
A12: =Comparison!B10 | B12: =Comparison!E10 | C12: =Comparison!AE10 | D12: =$C12*Assumptions!$B$15 | E12: =D12*30 | F12: =D12*Assumptions!$B$7 | G12: =F12*Assumptions!$B$6 | H12: =$C12*Assumptions!$B$16 | I12: =H12*30 | J12: =H12*Assumptions!$B$7 | K12: =J12*Assumptions!$B$6 | L12: =$C12*Assumptions!$B$17 | M12: =L12*30 | N12: =L12*Assumptions!$B$7 | O12: =N12*Assumptions!$B$6
A13: =Comparison!B11 | B13: =Comparison!E11 | C13: =Comparison!AE11 | D13: =$C13*Assumptions!$B$15 | E13: =D13*30 | F13: =D13*Assumptions!$B$7 | G13: =F13*Assumptions!$B$6 | H13: =$C13*Assumptions!$B$16 | I13: =H13*30 | J13: =H13*Assumptions!$B$7 | K13: =J13*Assumptions!$B$6 | L13: =$C13*Assumptions!$B$17 | M13: =L13*30 | N13: =L13*Assumptions!$B$7 | O13: =N13*Assumptions!$B$6
A15: Assumptions: petrol price and electricity rate from Assumptions sheet; monthly = 30 days. EV consumption includes ~12% charging loss.

Sheet 5-Year TCO
A1: 5-year Total Cost of Ownership (excludes resale value) – KNOWN: purchase price & fuel/power rates; ESTIMATED: everything on Assumptions rows 21–25
A3: Scooter | B3: Fuel | C3: On-road price (₹) | D3: S1 km in period | E3: S1 Energy/fuel | F3: S1 Other costs (est.) | G3: S1 TOTAL TCO | H3: S1 ₹ per km | I3: S2 km in period | J3: S2 Energy/fuel | K3: S2 Other costs (est.) | L3: S2 TOTAL TCO | M3: S2 ₹ per km | N3: S3 km in period | O3: S3 Energy/fuel | P3: S3 Other costs (est.) | Q3: S3 TOTAL TCO | R3: S3 ₹ per km
A4: =Comparison!B2 | B4: =Comparison!E2 | C4: =Comparison!P2 | D4: =Assumptions!$B$15*Assumptions!$B$7*Assumptions!$B$6 | E4: =D4*'Running Cost'!$C4 | F4: =IF(B4="EV",Assumptions!$B$26,Assumptions!$E$26) | G4: =$C4+E4+F4 | H4: =G4/D4 | I4: =Assumptions!$B$16*Assumptions!$B$7*Assumptions!$B$6 | J4: =I4*'Running Cost'!$C4 | K4: =IF(B4="EV",Assumptions!$C$26,Assumptions!$F$26) | L4: =$C4+J4+K4 | M4: =L4/I4 | N4: =Assumptions!$B$17*Assumptions!$B$7*Assumptions!$B$6 | O4: =N4*'Running Cost'!$C4 | P4: =IF(B4="EV",Assumptions!$D$26,Assumptions!$G$26) | Q4: =$C4+O4+P4 | R4: =Q4/N4
A5: =Comparison!B3 | B5: =Comparison!E3 | C5: =Comparison!P3 | D5: =Assumptions!$B$15*Assumptions!$B$7*Assumptions!$B$6 | E5: =D5*'Running Cost'!$C5 | F5: =IF(B5="EV",Assumptions!$B$26,Assumptions!$E$26) | G5: =$C5+E5+F5 | H5: =G5/D5 | I5: =Assumptions!$B$16*Assumptions!$B$7*Assumptions!$B$6 | J5: =I5*'Running Cost'!$C5 | K5: =IF(B5="EV",Assumptions!$C$26,Assumptions!$F$26) | L5: =$C5+J5+K5 | M5: =L5/I5 | N5: =Assumptions!$B$17*Assumptions!$B$7*Assumptions!$B$6 | O5: =N5*'Running Cost'!$C5 | P5: =IF(B5="EV",Assumptions!$D$26,Assumptions!$G$26) | Q5: =$C5+O5+P5 | R5: =Q5/N5
A6: =Comparison!B4 | B6: =Comparison!E4 | C6: =Comparison!P4 | D6: =Assumptions!$B$15*Assumptions!$B$7*Assumptions!$B$6 | E6: =D6*'Running Cost'!$C6 | F6: =IF(B6="EV",Assumptions!$B$26,Assumptions!$E$26) | G6: =$C6+E6+F6 | H6: =G6/D6 | I6: =Assumptions!$B$16*Assumptions!$B$7*Assumptions!$B$6 | J6: =I6*'Running Cost'!$C6 | K6: =IF(B6="EV",Assumptions!$C$26,Assumptions!$F$26) | L6: =$C6+J6+K6 | M6: =L6/I6 | N6: =Assumptions!$B$17*Assumptions!$B$7*Assumptions!$B$6 | O6: =N6*'Running Cost'!$C6 | P6: =IF(B6="EV",Assumptions!$D$26,Assumptions!$G$26) | Q6: =$C6+O6+P6 | R6: =Q6/N6
A7: =Comparison!B5 | B7: =Comparison!E5 | C7: =Comparison!P5 | D7: =Assumptions!$B$15*Assumptions!$B$7*Assumptions!$B$6 | E7: =D7*'Running Cost'!$C7 | F7: =IF(B7="EV",Assumptions!$B$26,Assumptions!$E$26) | G7: =$C7+E7+F7 | H7: =G7/D7 | I7: =Assumptions!$B$16*Assumptions!$B$7*Assumptions!$B$6 | J7: =I7*'Running Cost'!$C7 | K7: =IF(B7="EV",Assumptions!$C$26,Assumptions!$F$26) | L7: =$C7+J7+K7 | M7: =L7/I7 | N7: =Assumptions!$B$17*Assumptions!$B$7*Assumptions!$B$6 | O7: =N7*'Running Cost'!$C7 | P7: =IF(B7="EV",Assumptions!$D$26,Assumptions!$G$26) | Q7: =$C7+O7+P7 | R7: =Q7/N7
A8: =Comparison!B6 | B8: =Comparison!E6 | C8: =Comparison!P6 | D8: =Assumptions!$B$15*Assumptions!$B$7*Assumptions!$B$6 | E8: =D8*'Running Cost'!$C8 | F8: =IF(B8="EV",Assumptions!$B$26,Assumptions!$E$26) | G8: =$C8+E8+F8 | H8: =G8/D8 | I8: =Assumptions!$B$16*Assumptions!$B$7*Assumptions!$B$6 | J8: =I8*'Running Cost'!$C8 | K8: =IF(B8="EV",Assumptions!$C$26,Assumptions!$F$26) | L8: =$C8+J8+K8 | M8: =L8/I8 | N8: =Assumptions!$B$17*Assumptions!$B$7*Assumptions!$B$6 | O8: =N8*'Running Cost'!$C8 | P8: =IF(B8="EV",Assumptions!$D$26,Assumptions!$G$26) | Q8: =$C8+O8+P8 | R8: =Q8/N8
A9: =Comparison!B7 | B9: =Comparison!E7 | C9: =Comparison!P7 | D9: =Assumptions!$B$15*Assumptions!$B$7*Assumptions!$B$6 | E9: =D9*'Running Cost'!$C9 | F9: =IF(B9="EV",Assumptions!$B$26,Assumptions!$E$26) | G9: =$C9+E9+F9 | H9: =G9/D9 | I9: =Assumptions!$B$16*Assumptions!$B$7*Assumptions!$B$6 | J9: =I9*'Running Cost'!$C9 | K9: =IF(B9="EV",Assumptions!$C$26,Assumptions!$F$26) | L9: =$C9+J9+K9 | M9: =L9/I9 | N9: =Assumptions!$B$17*Assumptions!$B$7*Assumptions!$B$6 | O9: =N9*'Running Cost'!$C9 | P9: =IF(B9="EV",Assumptions!$D$26,Assumptions!$G$26) | Q9: =$C9+O9+P9 | R9: =Q9/N9
A10: =Comparison!B8 | B10: =Comparison!E8 | C10: =Comparison!P8 | D10: =Assumptions!$B$15*Assumptions!$B$7*Assumptions!$B$6 | E10: =D10*'Running Cost'!$C10 | F10: =IF(B10="EV",Assumptions!$B$26,Assumptions!$E$26) | G10: =$C10+E10+F10 | H10: =G10/D10 | I10: =Assumptions!$B$16*Assumptions!$B$7*Assumptions!$B$6 | J10: =I10*'Running Cost'!$C10 | K10: =IF(B10="EV",Assumptions!$C$26,Assumptions!$F$26) | L10: =$C10+J10+K10 | M10: =L10/I10 | N10: =Assumptions!$B$17*Assumptions!$B$7*Assumptions!$B$6 | O10: =N10*'Running Cost'!$C10 | P10: =IF(B10="EV",Assumptions!$D$26,Assumptions!$G$26) | Q10: =$C10+O10+P10 | R10: =Q10/N10
A11: =Comparison!B9 | B11: =Comparison!E9 | C11: =Comparison!P9 | D11: =Assumptions!$B$15*Assumptions!$B$7*Assumptions!$B$6 | E11: =D11*'Running Cost'!$C11 | F11: =IF(B11="EV",Assumptions!$B$26,Assumptions!$E$26) | G11: =$C11+E11+F11 | H11: =G11/D11 | I11: =Assumptions!$B$16*Assumptions!$B$7*Assumptions!$B$6 | J11: =I11*'Running Cost'!$C11 | K11: =IF(B11="EV",Assumptions!$C$26,Assumptions!$F$26) | L11: =$C11+J11+K11 | M11: =L11/I11 | N11: =Assumptions!$B$17*Assumptions!$B$7*Assumptions!$B$6 | O11: =N11*'Running Cost'!$C11 | P11: =IF(B11="EV",Assumptions!$D$26,Assumptions!$G$26) | Q11: =$C11+O11+P11 | R11: =Q11/N11
A12: =Comparison!B10 | B12: =Comparison!E10 | C12: =Comparison!P10 | D12: =Assumptions!$B$15*Assumptions!$B$7*Assumptions!$B$6 | E12: =D12*'Running Cost'!$C12 | F12: =IF(B12="EV",Assumptions!$B$26,Assumptions!$E$26) | G12: =$C12+E12+F12 | H12: =G12/D12 | I12: =Assumptions!$B$16*Assumptions!$B$7*Assumptions!$B$6 | J12: =I12*'Running Cost'!$C12 | K12: =IF(B12="EV",Assumptions!$C$26,Assumptions!$F$26) | L12: =$C12+J12+K12 | M12: =L12/I12 | N12: =Assumptions!$B$17*Assumptions!$B$7*Assumptions!$B$6 | O12: =N12*'Running Cost'!$C12 | P12: =IF(B12="EV",Assumptions!$D$26,Assumptions!$G$26) | Q12: =$C12+O12+P12 | R12: =Q12/N12
A13: =Comparison!B11 | B13: =Comparison!E11 | C13: =Comparison!P11 | D13: =Assumptions!$B$15*Assumptions!$B$7*Assumptions!$B$6 | E13: =D13*'Running Cost'!$C13 | F13: =IF(B13="EV",Assumptions!$B$26,Assumptions!$E$26) | G13: =$C13+E13+F13 | H13: =G13/D13 | I13: =Assumptions!$B$16*Assumptions!$B$7*Assumptions!$B$6 | J13: =I13*'Running Cost'!$C13 | K13: =IF(B13="EV",Assumptions!$C$26,Assumptions!$F$26) | L13: =$C13+J13+K13 | M13: =L13/I13 | N13: =Assumptions!$B$17*Assumptions!$B$7*Assumptions!$B$6 | O13: =N13*'Running Cost'!$C13 | P13: =IF(B13="EV",Assumptions!$D$26,Assumptions!$G$26) | Q13: =$C13+O13+P13 | R13: =Q13/N13
A15: Reading this honestly:
A16: • Resale NOT included: a 5-yr-old Activa/Jupiter may fetch ~₹35–45k vs ~₹20–35k for an out-of-warranty EV (estimate) – narrows but does not close the EV advantage.
A17: • Years 6–10: petrol keeps running on servicing alone; an EV will likely need a ₹45–60k battery somewhere in years 6–9 unless use is low.
A18: • 'Other costs' = servicing + consumables + insurance renewals + tyres + EV battery provision (Assumptions sheet, editable).

Sheet vs Your Pleasure
A1: Area | B1: Your Hero Honda Pleasure (~2015) | C1: New petrol (Activa / Jupiter / Pleasure+) | D1: EV (iQube / Chetak C25)
A2: Kerb weight | B2: ~104 kg | C2: 102–105 kg (same) | D2: 108–110 kg (+4 to +6 kg)
A3: Seat height | B3: 765 mm | C3: 764–770 mm (same) | D3: 763–770 mm (same)
A4: Dimensions | B4: 1,750 × 705 × 1,100 mm; 125 mm GC | C4: ~1,830–1,850 mm long; ~155–163 mm GC | D4: Similar
A5: Engine / motor | B5: 102 cc, 6.7 bhp, carburettor | C5: 110 cc, ~8 bhp, fuel injection, idle-stop | D5: 2.2–4.4 kW motor, instant torque
A6: Mileage / range | B6: ~45–50 kmpl now (ARAI 63) | C6: ~50–55 kmpl | D6: 75–90 km per charge (real)
A7: Storage | B7: Small | C7: 18 L (Activa) – 33 L (Jupiter) | D7: 25 L (C25); iQube – check
A8: Comfort / ride | B8: Soft but worn | C8: New suspension, longer seat | D8: Similar; slightly firmer
A9: Handling | B9: Very light | C9: Same feel; Pleasure+ closest | D9: Low centre of gravity, very easy
A10: Braking / safety | B10: Drum/drum, no CBS | C10: CBS, optional disc, LED lamps, side-stand cut-off | D10: CBS, disc (iQube), regen braking
A11: Reliability | B11: Proven but ageing | C11: Excellent | D11: Good; more electronics
A12: Maintenance cost | B12: Rising with age | C12: ~₹2,000–4,000/yr (est.) | D12: ~₹1,000–1,600/yr (est.)
... A19: Technology | B19: None | C19: TFT/Bluetooth/smart key on upper variants | D19: App, navigation, OTA (iQube/Ather)
A21: GAIN by replacing your Pleasure: CBS/LED safety, FI reliability + new warranty, ~10% (petrol) or ~90% (EV) lower energy cost, bigger boot, USB/digital features.
A22: LOSE by moving to EV: 2-minute refuels, roadside-mechanic freedom, range for unplanned 100 km+ trips, highway pace (C25), resale certainty; battery cliff ₹45–60k after warranty.
A23: GAIN by buying new petrol: zero learning curve, lowest upfront price, strongest resale, service anywhere, no battery risk – but you keep paying ~₹2/km.

Sheet Thoothukudi Dealers
A1: Brand | B1: Dealer | C1: Address | D1: Contact | E1: Sales | F1: Service | G1: Models of interest | H1: Status
A2: Honda | B2: Pearl Honda | C2: No. 5 & 6, Ettayapuram Rd, Tuticorin Melur, State Bank Colony – 628002 | D2: Not listed | E2: ✅ | F2: ✅ | G2: Activa 110; Activa e/QC1 ⚠️ | H2: Activa listed. QC1/Activa e: dealer/service availability not confirmed
A3: TVS | B3: Nellai Trading Automobile | C3: 16H/1, Palayamkottai Road – 628008 | D3: — | E3: ✅ | F3: ✅ | G3: Jupiter 110, iQube†, Orbiter† | H3: Listed TVS dealer – confirm iQube authorisation on dealers.tvsmotor.com/iqube
A4: TVS | B4: Mizbah Motors | C4: Ettayapuram Main Rd, near New Bus Stand – 628003 | D4: — | E4: ✅ | F4: ✅ | G4: Jupiter 110, iQube† | H4: Listed TVS dealer
A5: TVS (district) | B5: Sri Ganga Motors / Udhayam Motors / Suresh Motors / Shree Om Muruga Agency | C5: Kovilpatti Rd 628718 / 628617 / Kulasekarapattinam Rd 628203 / Pudur 628905 | D5: — | E5: ✅ | F5: ✅ | G5: — | H5: Outside city – back-up service
A6: Ather | B6: Ather – Thoothukudi Palayamkottai Road | C6: 7B, 7C, 7D Palayamkottai Rd – 628008 | D6: via atherenergy.com | E6: ✅ | F6: ✅ | G6: Rizta S | H6: Listed
A7: Bajaj | B7: Susee Bajaj | C7: 99-A, Ettayapuram Road – 628001 | D7: — | E7: ✅ | F7: ✅ | G7: Chetak C25 ⚠️ | H7: Chetak dealer/service availability not confirmed – check chetak.com locator
A8: Bajaj | B8: APT Autos | C8: 131/1 Palamkottai Road – 628215 | D8: — | E8: ✅ | F8: ✅ | G8: Chetak ⚠️ | H8: Chetak dealer/service availability not confirmed
A9: Hero | B9: Arvinth Auto Agency | C9: No 3/201, Korampallam – 628101 | D9: 93550 29428 | E9: ✅ | F9: ✅ | G9: Pleasure+ XTEC; Vida VX2 ⚠️ | H9: Pleasure+ listed. Vida: dealer/service availability not confirmed
A10: Suzuki | B10: Welcome Motors | C10: No. 99 College Teachers Colony, Tirunelveli–Thoothukudi Main Rd, Korampallam Post – 628101 | D10: 73737 06007 | E10: ✅ | F10: ✅ | G10: Access 125 | H10: Listed (only Suzuki outlet)
A11: Yamaha | B11: Lakhmi Motors | C11: 247–249 Muthu Mahal, Opp. KTC Depot, Tiruchendur Rd – 628216 | D11: 73737 30152 | E11: ✅ | F11: ✅ | G11: Fascino 125 | H11: Listed
A12: Yamaha | B12: Devi Motors | C12: 1/201/1A Main Rd, Puthiamputhur – 628402 | D12: 87543 85656 | E12: ✅ | F12: ✅ | G12: Fascino 125 | H12: Listed (outside city)
A14: Source: dealer directories (BikeWale, Bikes4Sale, CarBike360) via search, Oct 2026. Verify on each brand's official dealer locator before paying.

Sheet Rankings & Shortlist
A1: Top 5 EV
A2: 1 | B2: TVS iQube 2.2 kWh | C2: Proven EV, densest authorised network in Thoothukudi, light enough, quick; 5 yr/70k battery extension.
A3: 2 | B3: Bajaj Chetak C25 | C3: Best value & best weight-to-range (108 kg, ~90 km, ~₹96.5k); 55 km/h cap and unconfirmed local Chetak service.
A4: 3 | B4: TVS Orbiter V1 | C4: Lightest practical EV (101 kg, 760 mm, 34 L) with TVS backing; small battery = ≤40 km/day.
A5: 4 | B5: Ather Rizta S | C5: Best EV product (range, comfort, confirmed local centre) but 119 kg and ~₹30k dearer.
A6: 5 | B6: Hero Vida VX2 Go | C6: Removable battery & 5-yr battery warranty, but local Vida sales/service unconfirmed.
A8: Top 5 Petrol
A9: 1 | B9: Honda Activa 110 | C9: Unbeatable reliability & resale; same weight/seat as your Pleasure; warranty to 10 yrs; city dealer.
A10: 2 | B10: TVS Jupiter 110 | C10: Most practical: 33 L boot, front fuel filler, disc option, iGO assist, 5-yr warranty, several local dealers.
A11: 3 | B11: Hero Pleasure+ XTEC | C11: Cheapest (₹86.6k), lowest ₹/kg, most familiar; LED projector + Bluetooth + i3S.
A12: 4 | B12: Suzuki Access 125 | C12: Light 125cc with the smoothest engine; slightly lower mileage; one local outlet.
A13: 5 | B13: Yamaha Fascino 125 Hybrid | C13: Lightest petrol (99 kg), frugal; taller seat, small boot, cramped pillion.
A15: Final Shortlist
A16: Category | B16: Scooter | C16: Weight (kg) | D16: Price (₹ on-road) | E16: Range / Mileage | F16: Why buy
A17: Best EV | B17: TVS iQube 2.2 kWh | C17: =Comparison!F3 | D17: =Comparison!P3 | E17: 75 km real | F17: Proven, quick, strongest local EV service
A18: Best Lightweight EV | B18: TVS Orbiter V1 | C18: =Comparison!F7 | D18: =Comparison!P7 | E18: ~65–75 km (est.) | F18: Lightest full-size EV, 34 L boot, TVS network
A19: Best Value EV | B19: Bajaj Chetak C25 | C19: =Comparison!F5 | D19: =Comparison!P5 | E19: ~90 km real | F19: Lowest 5-yr cost, best range/kg among light EVs
A20: Best Petrol | B20: Honda Activa 110 | C20: =Comparison!F2 | D20: =Comparison!P2 | E20: ~50 kmpl | F20: 10-year reliability, resale, extended warranty
A21: Best Lightweight Petrol | B21: Yamaha Fascino 125 Hybrid | C21: =Comparison!F10 | D21: =Comparison!P10 | E21: ~50–55 kmpl | F21: Lightest petrol, frugal hybrid assist
A22: Best Value Petrol | B22: Hero Pleasure+ XTEC | C22: =Comparison!F6 | D22: =Comparison!P6 | E22: ~48–54 kmpl | F22: Cheapest; feels like your Pleasure
A23: Best Long-Term (5–10 yr) | B23: Honda Activa 110 | C23: =Comparison!F2 | D23: =Comparison!P2 | E23: ~50 kmpl | F23: No battery cliff, best resale, service everywhere
A25: FINAL TOP 3
A26: 🥇 1st: TVS iQube 2.2 kWh (+ 5 yr/70k battery extension) – if you have home charging and ride ≤45 km/day (3.1 kWh if more).
A27: 🥈 2nd: Honda Activa 110 (DLX/H-Smart) – if no home charging or you want a no-surprises 10-year scooter. (Alt: TVS Jupiter 110 for the 33 L boot.)
A28: 🥉 3rd: Bajaj Chetak C25 – EV under ₹1 lakh with ~90 km real range; confirm local Chetak service in writing first.
A29: EV vs Petrol: <15 km/day → petrol; 15–45 km/day with home charging → EV; no home charging → petrol; 45–70 km/day with charging → iQube 3.1 / Rizta; >70 km/day or frequent highway → petrol.

Sheet Sources
A1: Topic | B1: Source (accessed 5 Oct 2026)
A2: PM E-DRIVE subsidy end | B2: https://www.evfy.in/news/pm-e-drive-subsidy-ends-what-it-means-for-ev-buyers-from-august-2026
A3: PM E-DRIVE extension to 31 Jul 2026 | B3: https://www.autocarindia.com/bike-news/pm-e-drive-subsidy-extended-until-july-31-for-electric-two-wheelers-439316
A4: TN EV road-tax exemption | B4: https://thefederal.com/category/states/south/tamil-nadu/tamil-nadu-ev-road-tax-exemption-till-dec-31-2027-223729
A5: TN electricity tariff 2026 | B5: https://thediscombill.com/guides/tamil-nadu-electricity-tariff-july-2026/
A6: Thoothukudi petrol price | B6: https://www.shriramfinance.in/petrol-price-in-thoothukudi
A7: Battery replacement costs | B7: https://www.evfy.in/news/battery-replacement-costs-of-ev-two-wheelers-in-india
A8: TVS iQube specs | B8: https://www.autocarindia.com/bikes/tvs/iqube/specifications
A9: TVS iQube 2.2 real-world range | B9: https://tvsmotor.com/electric-vehicle/tvs-iqube/tvs-iqube-2-2-kwh-variant-details
A10: TVS warranty policy | B10: https://www.tvsmotor.com/customers/Warranty-Policy
A11: Bajaj Chetak C25 specs | B11: https://www.91wheels.com/scooters/bajaj/chetak-c25
A12: Chetak C25 first ride | B12: https://www.rushlane.com/bajaj-chetak-c25-first-ride-review-your-next-ev-under-rs-1-lakh-12538166.html
... A37: Owner complaints – iQube | B37: https://www.multibagg.ai/market-pulse/articles/tvs-iqube-complaints-ev-impact-cmr7a5zp3pmrvqs0jabjoamwr
