Workbook

Sheet README
A1: Vehicle Feature Coverage Workbook
A2: Research date | B2: 13 October 2026
A3: Purpose | B3: Compares exact vehicle variants in India, the UK and the USA against a fixed checklist of 24 safety features taken from the Automotive Safety Systems training deck.
A4: Coverage formula | B4: Verified coverage (%) = (features with status Y or R) ÷ 24 × 100. The same 24-feature denominator is used for every vehicle.
A5: Indicative coverage | B5: Adds features with status M (official model-level evidence whose fit on the exact variant is not confirmed). Shown for context only; bands use verified coverage.
A6: Bands | B6: 100% = all 24 verified · 75% band = 75–99% · 50% band = 50–74% · 25% band = 25–49% · Below 25% = under 25%. Percentages are never rounded up into a higher band.
A7: Status Y | B7: Present – verified for exact variant
A8: Status R | B8: Present – required by law in this market
A9: Status M | B9: Model-level evidence only – exact variant not confirmed
A10: Status N | B10: Absent – verified not offered on this variant
A11: Status U | B11: Unconfirmed – no reliable evidence found
A12: How evidence was gathered | B12: Official manufacturer pages, brochures, press releases, specification sheets, owner's manuals and regulators were located with web search restricted to each manufacturer's or regulator's own domain, and claims were taken from those search extracts. Direct page fetching was unavailable in the research environment, so some brochure tables could not be read in full. Unconfirmed (U) therefore often means 'not shown in the official extracts', not 'absent'.
A13: Limitations | B13: A sample of nine variants, not a census of the market. Post-crash functions (crash unlock/hazards, fuel or high-voltage cut-off, EDR) are rarely stated in official specification documents, so they are mostly unconfirmed. Equipment changes with model year; re-check before reuse.
... A15: Sheets | B15: Checklist · Coverage Matrix · Evidence (one row per vehicle × feature, filterable) · Band Summary · Source Register

Sheet Checklist
A1: Code | B1: Layer | C1: Feature | D1: Simple meaning
A2: A1 | B2: Active safety | C2: ABS (anti-lock brakes) | D2: Stops wheels locking so you can still steer
A3: A2 | B3: Active safety | C3: EBD (brake-force distribution) | D3: Shares braking force to suit the load
A4: A3 | B4: Active safety | C4: Brake Assist | D4: Adds braking force in a panic stop
A5: A4 | B5: Active safety | C5: ESC (stability control) | D5: Brakes individual wheels to stop a skid
A6: A5 | B6: Active safety | C6: Traction control | D6: Stops wheelspin when pulling away
A7: A6 | B7: Active safety | C7: TPMS (tyre-pressure monitoring) | D7: Warns of an under-inflated tyre
A8: A7 | B8: Active safety | C8: Hill Start Assist | D8: Stops roll-back when starting on a slope
A9: A8 | B9: Active safety | C9: Hill Descent Control | D9: Holds a slow speed down steep slopes
A10: A9 | B10: Active safety | C10: Electric parking brake with Auto Hold | D10: Holds the car at stops without the pedal
A11: D1 | B11: ADAS | C11: Forward Collision Warning | D11: Warns when closing in too fast
A12: D2 | B12: ADAS | C12: Automatic Emergency Braking | D12: Brakes by itself if a crash is imminent
... A25: C4 | B25: Post-crash | C25: Event Data Recorder (EDR) | D25: Stores a short snapshot around a crash
A27: Total features in checklist | C27: =COUNTA(A2:A25) -> 24
A29: Excluded from scoring
A30: — | C30: Crumple zones and rigid safety cell | D30: Designed into every modern car body; not a fitted or optional item, so it cannot separate one variant from another.
A31: — | C31: Three-point seatbelts and head restraints | D31: Legally required in all three markets reviewed; present on every car in the sample.
A32: — | C32: Knee airbag | D32: Mentioned only in the presenter notes of the original deck; kept out so airbags are not counted twice.
A33: — | C33: Pedestrian protection (active bonnet / pedestrian airbag) | D33: Rare and model-specific; pedestrian-friendly design is a type-approval matter rather than a fitted feature.

Sheet Coverage Matrix
A1: Market | B1: Manufacturer | C1: Model | D1: Exact variant | E1: Model year / period | F1: Powertrain | G1: A1 ABS (anti-lock brakes) | H1: A2 EBD (brake-force distribution) | I1: A3 Brake Assist | J1: A4 ESC (stability control) | K1: A5 Traction control | L1: A6 TPMS (tyre-pressure monitoring) | M1: A7 Hill Start Assist | N1: A8 Hill Descent Control | O1: A9 Electric parking brake with Auto Hold | P1: D1 Forward Collision Warning | Q1: D2 Automatic Emergency Braking | R1: D3 Adaptive Cruise Control | S1: D4 Lane Departure Warning | T1: D5 Lane Keeping Assist | U1: D6 Blind Spot Monitoring | V1: D7 Rear Cross Traffic Alert | W1: P1 Front, side & curtain airbags (6+) | X1: P2 Seatbelt pretensioners | Y1: P3 Seatbelt load limiters | Z1: P4 ISOFIX / LATCH child-seat anchors | AA1: C1 Emergency call / SOS (eCall) | AB1: C2 Crash-triggered hazard lights / door unlock | AC1: C3 Fuel cut-off or high-voltage isolation | AD1: C4 Event Data Recorder (EDR) | AE1: Present (Y+R) | AF1: Model-level (M) | AG1: Absent (N) | AH1: Unconfirmed (U) | AI1: Checklist total | AJ1: Verified coverage | AK1: Indicative coverage (incl. M) | AL1: Coverage band | AM1: Official sources used
A2: India | B2: Hyundai | C2: Creta | D2: King (automatic: IVT/DCT) | E2: 2026 (current India line-up, Oct 2026) | F2: Petrol/diesel (ICE) | G2: R | H2: U | I2: U | J2: Y | K2: U | L2: Y | M2: Y | N2: U | O2: Y | P2: Y | Q2: Y | R2: Y | S2: U | T2: Y | U2: M | V2: M | W2: Y | X2: Y | Y2: U | Z2: Y | AA2: M | AB2: U | AC2: U | AD2: U | AE2: =COUNTIF(G2:AD2,"Y")+COUNTIF(G2:AD2,"R") -> 12 | AF2: =COUNTIF(G2:AD2,"M") -> 3 | AG2: =COUNTIF(G2:AD2,"N") -> 0 | AH2: =COUNTIF(G2:AD2,"U") -> 9 | AI2: =Checklist!$C$27 -> 24 | AJ2: =IF(AI2=0,0,AE2/AI2) -> 0.5 | AK2: =IF(AI2=0,0,(AE2+AF2)/AI2) -> 0.625 | AL2: =IF(AJ2>=1,"100% – Complete",IF(AJ2>=0.75,"75% band (75–99%)",IF(AJ2>=0.5,"50% band (50–74%)",IF(AJ2>=0.25,"25% band (25–49%)","Below 25%")))) -> 50% band (50–74%) | AM2: https://www.hyundai.com/in/en/blog/hyundai-creta-advance-features-specs-guide | https://www.hyundai.com/content/dam/hyundai/in/en/data/brochure/creta.pdf | https://www.hyundai.com/content/dam/hyundai/in/en/data/brochure/creta-brochureknight.pdf | https://www.hyundai.com/in/en/find-a-car/creta/features | https://www.hyundai.com/in/en/find-a-car/creta/price | https://www.hyundai.com/in/en/find-a-car/creta/safety | https://www.hyundai.com/in/en/blog/hyundai-creta-car-variants-explained | https://www.autocarindia.com/car-news/new-cars-and-bikes-to-get-more-safety-tech-this-year-411018
A3: India | B3: Mahindra | C3: XEV 9e | D3: Pack Three | E3: 2025–26 | F3: Battery electric | G3: R | H3: U | I3: M | J3: Y | K3: U | L3: Y | M3: M | N3: M | O3: M | P3: Y | Q3: Y | R3: M | S3: U | T3: Y | U3: Y | V3: Y | W3: Y | X3: M | Y3: U | Z3: Y | AA3: M | AB3: U | AC3: U | AD3: U | AE3: =COUNTIF(G3:AD3,"Y")+COUNTIF(G3:AD3,"R") -> 10 | AF3: =COUNTIF(G3:AD3,"M") -> 7 | AG3: =COUNTIF(G3:AD3,"N") -> 0 | AH3: =COUNTIF(G3:AD3,"U") -> 7 | AI3: =Checklist!$C$27 -> 24 | AJ3: =IF(AI3=0,0,AE3/AI3) -> 0.41666667 | AK3: =IF(AI3=0,0,(AE3+AF3)/AI3) -> 0.70833333 | AL3: =IF(AJ3>=1,"100% – Complete",IF(AJ3>=0.75,"75% band (75–99%)",IF(AJ3>=0.5,"50% band (50–74%)",IF(AJ3>=0.25,"25% band (25–49%)","Below 25%")))) -> 25% band (25–49%) | AM3: https://www.autocarindia.com/car-news/new-cars-and-bikes-to-get-more-safety-tech-this-year-411018 | https://www.mahindraelectricsuv.com/on/demandware.static/-/Library-Sites-eSUVSharedLibrary/default/MXV9/XEV9e_BROCHURE_R1_20260428.pdf | https://www.mahindraelectricsuv.com/faq.html | https://booking.mahindra.com/on/demandware.static/-/Library-Sites-eSUVSharedLibrary/default/dw5ad7dd6c/OwnerManual/XEV_9e_HTML/XEV9e-OM.html | https://auto.mahindra.com/press-release/xev-nine-e-and-be-six-create-history.html | https://auto.mahindra.com/press-release/mahindra-democratises-premium-ev-technology-announces-top-variant-prices-of-be-6-and-xev-9e.html
A4: India | B4: Škoda | C4: Kylaq | D4: Prestige+ (top variant) | E4: 2025–26 | F4: Petrol (ICE) | G4: Y | H4: Y | I4: U | J4: Y | K4: M | L4: M | M4: M | N4: U | O4: U | P4: U | Q4: U | R4: U | S4: U | T4: U | U4: U | V4: U | W4: Y | X4: U | Y4: U | Z4: Y | AA4: U | AB4: U | AC4: U | AD4: U | AE4: =COUNTIF(G4:AD4,"Y")+COUNTIF(G4:AD4,"R") -> 5 | AF4: =COUNTIF(G4:AD4,"M") -> 3 | AG4: =COUNTIF(G4:AD4,"N") -> 0 | AH4: =COUNTIF(G4:AD4,"U") -> 16 | AI4: =Checklist!$C$27 -> 24 | AJ4: =IF(AI4=0,0,AE4/AI4) -> 0.20833333 | AK4: =IF(AI4=0,0,(AE4+AF4)/AI4) -> 0.33333333 | AL4: =IF(AJ4>=1,"100% – Complete",IF(AJ4>=0.75,"75% band (75–99%)",IF(AJ4>=0.5,"50% band (50–74%)",IF(AJ4>=0.25,"25% band (25–49%)","Below 25%")))) -> Below 25% | AM4: https://www.skoda-auto.co.in/news/news-detail/skoda-kylaq-marks-one-year-landmark-by-celebrating-50k-sales-milestone | https://www.skoda-auto.co.in/_doc/54fc9665-9adc-4e0e-97ae-0a6b798d59c2 | https://www.skoda-storyboard.com/en/press-releases/the-all-new-skoda-kylaq-a-new-era-for-skoda-in-indias-popular-sub-4-metre-suv-segment/ | https://www.skoda-auto.co.in/shopping/kylaq-safety
A5: India | B5: Maruti Suzuki | C5: Swift | D5: ZXi+ | E5: 2024– (4th generation) | F5: Petrol (ICE) | G5: Y | H5: Y | I5: Y | J5: Y | K5: U | L5: U | M5: Y | N5: U | O5: U | P5: U | Q5: U | R5: U | S5: U | T5: U | U5: U | V5: U | W5: Y | X5: Y | Y5: Y | Z5: Y | AA5: U | AB5: U | AC5: U | AD5: U | AE5: =COUNTIF(G5:AD5,"Y")+COUNTIF(G5:AD5,"R") -> 9 | AF5: =COUNTIF(G5:AD5,"M") -> 0 | AG5: =COUNTIF(G5:AD5,"N") -> 0 | AH5: =COUNTIF(G5:AD5,"U") -> 15 | AI5: =Checklist!$C$27 -> 24 | AJ5: =IF(AI5=0,0,AE5/AI5) -> 0.375 | AK5: =IF(AI5=0,0,(AE5+AF5)/AI5) -> 0.375 | AL5: =IF(AJ5>=1,"100% – Complete",IF(AJ5>=0.75,"75% band (75–99%)",IF(AJ5>=0.5,"50% band (50–74%)",IF(AJ5>=0.25,"25% band (25–49%)","Below 25%")))) -> 25% band (25–49%) | AM5: https://www.marutisuzuki.com/arena/swift | https://www.marutisuzuki.com/corporate/media/press-releases/2024/may/ms-launches-epic-new-swift-with-all-new-z-series-engine | https://marutisuzuki.com/cng/swift
A6: India | B6: Maruti Suzuki | C6: Alto K10 | D6: Any variant (features stated standard on all variants) | E6: 2025–26 | F6: Petrol/CNG (ICE) | G6: Y | H6: Y | I6: U | J6: Y | K6: U | L6: U | M6: M | N6: U | O6: U | P6: U | Q6: U | R6: U | S6: U | T6: U | U6: U | V6: U | W6: Y | X6: U | Y6: U | Z6: U | AA6: U | AB6: U | AC6: U | AD6: U | AE6: =COUNTIF(G6:AD6,"Y")+COUNTIF(G6:AD6,"R") -> 4 | AF6: =COUNTIF(G6:AD6,"M") -> 1 | AG6: =COUNTIF(G6:AD6,"N") -> 0 | AH6: =COUNTIF(G6:AD6,"U") -> 19 | AI6: =Checklist!$C$27 -> 24 | AJ6: =IF(AI6=0,0,AE6/AI6) -> 0.16666667 | AK6: =IF(AI6=0,0,(AE6+AF6)/AI6) -> 0.20833333 | AL6: =IF(AJ6>=1,"100% – Complete",IF(AJ6>=0.75,"75% band (75–99%)",IF(AJ6>=0.5,"50% band (50–74%)",IF(AJ6>=0.25,"25% band (25–49%)","Below 25%")))) -> Below 25% | AM6: https://www.marutisuzuki.com/arena/alto-k10 | https://www.marutisuzuki.com/corporate/media/press-releases/2025/may/maruti-suzuki-arena-enhances-safety-by-offering-6-airbags-as-standard | https://www.marutisuzuki.com/corporate/media/press-releases/2024/august/maruti-suzuki-offers-electronic-stability-program
A7: United Kingdom | B7: Volvo | C7: XC90 | D7: T8 plug-in hybrid, Core grade | E7: MY2025 (updated XC90) | F7: Plug-in hybrid | G7: U | H7: U | I7: U | J7: U | K7: U | L7: U | M7: Y | N7: Y | O7: U | P7: Y | Q7: Y | R7: Y | S7: M | T7: M | U7: M | V7: M | W7: M | X7: M | Y7: U | Z7: U | AA7: U | AB7: U | AC7: U | AD7: U | AE7: =COUNTIF(G7:AD7,"Y")+COUNTIF(G7:AD7,"R") -> 5 | AF7: =COUNTIF(G7:AD7,"M") -> 6 | AG7: =COUNTIF(G7:AD7,"N") -> 0 | AH7: =COUNTIF(G7:AD7,"U") -> 13 | AI7: =Checklist!$C$27 -> 24 | AJ7: =IF(AI7=0,0,AE7/AI7) -> 0.20833333 | AK7: =IF(AI7=0,0,(AE7+AF7)/AI7) -> 0.45833333 | AL7: =IF(AJ7>=1,"100% – Complete",IF(AJ7>=0.75,"75% band (75–99%)",IF(AJ7>=0.5,"50% band (50–74%)",IF(AJ7>=0.25,"25% band (25–49%)","Below 25%")))) -> Below 25% | AM7: https://www.volvocars.com/uk/cars/xc90-hybrid/specifications/ | https://www.volvocars.com/uk/news/safety/new-and-improved-the-best-ever-volvo-xc90/ | https://www.volvocars.com/ie/support/car/xc90/article/ | https://www.volvocars.com/uk/cars/new-models/xc90/specifications
A8: United States | B8: Hyundai | C8: IONIQ 5 N | D8: IONIQ 5 N (single trim) | E8: MY2026 | F8: Battery electric | G8: Y | H8: U | I8: Y | J8: Y | K8: Y | L8: Y | M8: Y | N8: U | O8: Y | P8: U | Q8: U | R8: Y | S8: U | T8: Y | U8: Y | V8: Y | W8: Y | X8: M | Y8: M | Z8: M | AA8: Y | AB8: U | AC8: U | AD8: U | AE8: =COUNTIF(G8:AD8,"Y")+COUNTIF(G8:AD8,"R") -> 13 | AF8: =COUNTIF(G8:AD8,"M") -> 3 | AG8: =COUNTIF(G8:AD8,"N") -> 0 | AH8: =COUNTIF(G8:AD8,"U") -> 8 | AI8: =Checklist!$C$27 -> 24 | AJ8: =IF(AI8=0,0,AE8/AI8) -> 0.54166667 | AK8: =IF(AI8=0,0,(AE8+AF8)/AI8) -> 0.66666667 | AL8: =IF(AJ8>=1,"100% – Complete",IF(AJ8>=0.75,"75% band (75–99%)",IF(AJ8>=0.5,"50% band (50–74%)",IF(AJ8>=0.25,"25% band (25–49%)","Below 25%")))) -> 50% band (50–74%) | AM8: https://www.hyundainews.com/assets/documents/original/68164-2026IONIQ5NSpecsFeatures20250722A.pdf | https://www.hyundainews.com/assets/documents/original/59548-IONIQ5NSpecs040424.pdf | https://www.hyundainews.com/releases/3761?lang=en_US | https://owners.hyundaiusa.com/content/dam/hyundai/us/myhyundai/manuals/erg/2022/ioniq-5/Ioniq5-erg.pdf | https://www.hyundainews.com/releases/4513 | https://www.nhtsa.gov/document/electronic-stability-control-systems-fmvss-no-126 | https://www.nhtsa.gov/sites/nhtsa.gov/files/fmvss/tirepressure-fmvss-138.pdf
A9: United States | B9: Tesla | C9: Model Y | D9: Premium (Long Range) | E9: 2025+ (MY2026, software 2026.32) | F9: Battery electric | G9: M | H9: U | I9: U | J9: R | K9: U | L9: Y | M9: U | N9: U | O9: U | P9: Y | Q9: Y | R9: Y | S9: M | T9: Y | U9: M | V9: U | W9: M | X9: M | Y9: U | Z9: U | AA9: M | AB9: U | AC9: M | AD9: M | AE9: =COUNTIF(G9:AD9,"Y")+COUNTIF(G9:AD9,"R") -> 6 | AF9: =COUNTIF(G9:AD9,"M") -> 8 | AG9: =COUNTIF(G9:AD9,"N") -> 0 | AH9: =COUNTIF(G9:AD9,"U") -> 10 | AI9: =Checklist!$C$27 -> 24 | AJ9: =IF(AI9=0,0,AE9/AI9) -> 0.25 | AK9: =IF(AI9=0,0,(AE9+AF9)/AI9) -> 0.58333333 | AL9: =IF(AJ9>=1,"100% – Complete",IF(AJ9>=0.75,"75% band (75–99%)",IF(AJ9>=0.5,"50% band (50–74%)",IF(AJ9>=0.25,"25% band (25–49%)","Below 25%")))) -> 25% band (25–49%) | AM9: https://www.nhtsa.gov/document/electronic-stability-control-systems-fmvss-no-126 | https://www.nhtsa.gov/sites/nhtsa.gov/files/fmvss/tirepressure-fmvss-138.pdf | https://digitalassets.tesla.com/tesla-contents/image/upload/2025-Model-Y-Emergency-Response-Guide.pdf | https://www.tesla.com/modely | https://www.tesla.com/ownersmanual/modely/en_us/Owners_Manual.pdf | https://www.tesla.com/ownersmanual/modely/en_us/GUID-2E8E5E0B-DAA8-40B8-9804-45F5960538DF.html | https://www.tesla.com/ownersmanual/modely/en_us/GUID-3319C55D-F148-4D9C-98A6-AD09BA7EED61.html | https://www.tesla.com/ownersmanual/modely/en_us/GUID-101D1BF5-52D2-469A-A57D-E7230BBEE94B.html | https://www.tesla.com/support/vehicle-safety-security-features
A10: United Kingdom | B10: Dacia | C10: Sandero | D10: Essential (entry trim) | E10: 2025–26 (GSR2-compliant) | F10: Petrol (ICE) | G10: Y | H10: U | I10: Y | J10: Y | K10: U | L10: Y | M10: Y | N10: U | O10: U | P10: U | Q10: Y | R10: N | S10: Y | T10: Y | U10: N | V10: U | W10: Y | X10: U | Y10: U | Z10: Y | AA10: Y | AB10: U | AC10: U | AD10: U | AE10: =COUNTIF(G10:AD10,"Y")+COUNTIF(G10:AD10,"R") -> 11 | AF10: =COUNTIF(G10:AD10,"M") -> 0 | AG10: =COUNTIF(G10:AD10,"N") -> 2 | AH10: =COUNTIF(G10:AD10,"U") -> 11 | AI10: =Checklist!$C$27 -> 24 | AJ10: =IF(AI10=0,0,AE10/AI10) -> 0.45833333 | AK10: =IF(AI10=0,0,(AE10+AF10)/AI10) -> 0.45833333 | AL10: =IF(AJ10>=1,"100% – Complete",IF(AJ10>=0.75,"75% band (75–99%)",IF(AJ10>=0.5,"50% band (50–74%)",IF(AJ10>=0.25,"25% band (25–49%)","Below 25%")))) -> 25% band (25–49%) | AM10: https://www.dacia.co.uk/vehicles/sandero/configurator.html | https://www.press.dacia.co.uk/releases/440 | https://www.press.dacia.co.uk/assets/documents/original/3930-DaciaSanderoandSanderoStepwayPressKitApril2022.pdf | https://www.press.dacia.co.uk/assets/documents/original/4592-DaciaSanderoandSanderoStepwayPressKitMay2023.pdf | https://www.dacia.co.uk/vehicles/sandero.html
A12: Legend
A13: Y | B13: Present – verified for exact variant
A14: R | B14: Present – required by law in this market
A15: M | B15: Model-level evidence only – exact variant not confirmed
A16: N | B16: Absent – verified not offered on this variant
A17: U | B17: Unconfirmed – no reliable evidence found
A19: Verified coverage = Present (Y+R) ÷ Checklist total. Indicative coverage adds Model-level (M). Source: research performed 13 October 2026; evidence per cell in the 'Evidence' sheet.

Sheet Evidence
A1: Market | B1: Manufacturer | C1: Model | D1: Exact variant | E1: Model year | F1: Feature code | G1: Layer | H1: Feature | I1: Status | J1: Status meaning | K1: Evidence note | L1: Source IDs | M1: Source URLs
A2: India | B2: Hyundai | C2: Creta | D2: King (automatic: IVT/DCT) | E2: 2026 (current India line-up, Oct 2026) | F2: A1 | G2: Active safety | H2: ABS (anti-lock brakes) | I2: R | J2: Present – required by law in this market | K2: Legal requirement in India since April 2019; ABS also named in Hyundai's lineup summaries. | L2: LAW-IN-ABS, HY-IN-VAR | M2: https://www.autocarindia.com/car-news/new-cars-and-bikes-to-get-more-safety-tech-this-year-411018 | https://www.hyundai.com/in/en/blog/hyundai-creta-car-variants-explained
A3: India | B3: Hyundai | C3: Creta | D3: King (automatic: IVT/DCT) | E3: 2026 (current India line-up, Oct 2026) | F3: A2 | G3: Active safety | H3: EBD (brake-force distribution) | I3: U | J3: Unconfirmed – no reliable evidence found | K3: Not found tied to King.
A4: India | B4: Hyundai | C4: Creta | D4: King (automatic: IVT/DCT) | E4: 2026 (current India line-up, Oct 2026) | F4: A3 | G4: Active safety | H4: Brake Assist | I4: U | J4: Unconfirmed – no reliable evidence found | K4: Not found.
A5: India | B5: Hyundai | C5: Creta | D5: King (automatic: IVT/DCT) | E5: 2026 (current India line-up, Oct 2026) | F5: A4 | G5: Active safety | H5: ESC (stability control) | I5: Y | J5: Present – verified for exact variant | K5: Hyundai variant guide: King carries ESC. | L5: HY-IN-VAR | M5: https://www.hyundai.com/in/en/blog/hyundai-creta-car-variants-explained
A6: India | B6: Hyundai | C6: Creta | D6: King (automatic: IVT/DCT) | E6: 2026 (current India line-up, Oct 2026) | F6: A5 | G6: Active safety | H6: Traction control | I6: U | J6: Unconfirmed – no reliable evidence found | K6: Only drive/traction modes mentioned; traction control not confirmed.
A7: India | B7: Hyundai | C7: Creta | D7: King (automatic: IVT/DCT) | E7: 2026 (current India line-up, Oct 2026) | F7: A6 | G7: Active safety | H7: TPMS (tyre-pressure monitoring) | I7: Y | J7: Present – verified for exact variant | K7: TPMS (Highline) listed across all trims; King carries TPMS. | L7: HY-IN-BROCH, HY-IN-VAR | M7: https://www.hyundai.com/content/dam/hyundai/in/en/data/brochure/creta.pdf | https://www.hyundai.com/in/en/blog/hyundai-creta-car-variants-explained
A8: India | B8: Hyundai | C8: Creta | D8: King (automatic: IVT/DCT) | E8: 2026 (current India line-up, Oct 2026) | F8: A7 | G8: Active safety | H8: Hill Start Assist | I8: Y | J8: Present – verified for exact variant | K8: Hill-start Assist Control listed as lineup-wide safety equipment. | L8: HY-IN-PRICE, HY-IN-SAFETY | M8: https://www.hyundai.com/in/en/find-a-car/creta/price | https://www.hyundai.com/in/en/find-a-car/creta/safety
A9: India | B9: Hyundai | C9: Creta | D9: King (automatic: IVT/DCT) | E9: 2026 (current India line-up, Oct 2026) | F9: A8 | G9: Active safety | H9: Hill Descent Control | I9: U | J9: Unconfirmed – no reliable evidence found | K9: Hill Descent Control confirmed only for Creta Electric, not this model.
A10: India | B10: Hyundai | C10: Creta | D10: King (automatic: IVT/DCT) | E10: 2026 (current India line-up, Oct 2026) | F10: A9 | G10: Active safety | H10: Electric parking brake with Auto Hold | I10: Y | J10: Present – verified for exact variant | K10: Feature table marks EPB with Auto Hold standard on King and King Knight. | L10: HY-IN-BROCH-K, HY-IN-FEAT | M10: https://www.hyundai.com/content/dam/hyundai/in/en/data/brochure/creta-brochureknight.pdf | https://www.hyundai.com/in/en/find-a-car/creta/features
A11: India | B11: Hyundai | C11: Creta | D11: King (automatic: IVT/DCT) | E11: 2026 (current India line-up, Oct 2026) | F11: D1 | G11: ADAS | H11: Forward Collision Warning | I11: Y | J11: Present – verified for exact variant | K11: King offers Forward Collision-Avoidance Assist (warns, then brakes). | L11: HY-IN-ADV, HY-IN-SAFETY | M11: https://www.hyundai.com/in/en/blog/hyundai-creta-advance-features-specs-guide | https://www.hyundai.com/in/en/find-a-car/creta/safety
A12: India | B12: Hyundai | C12: Creta | D12: King (automatic: IVT/DCT) | E12: 2026 (current India line-up, Oct 2026) | F12: D2 | G12: ADAS | H12: Automatic Emergency Braking | I12: Y | J12: Present – verified for exact variant | K12: Forward Collision-Avoidance Assist applies brakes automatically. | L12: HY-IN-ADV, HY-IN-SAFETY | M12: https://www.hyundai.com/in/en/blog/hyundai-creta-advance-features-specs-guide | https://www.hyundai.com/in/en/find-a-car/creta/safety
A13: India | B13: Hyundai | C13: Creta | D13: King (automatic: IVT/DCT) | E13: 2026 (current India line-up, Oct 2026) | F13: D3 | G13: ADAS | H13: Adaptive Cruise Control | I13: Y | J13: Present – verified for exact variant | K13: Brochure: Smart Cruise Control on King with AT/DCT/IVT (manual King excluded). | L13: HY-IN-BROCH-K, HY-IN-ADV | M13: https://www.hyundai.com/content/dam/hyundai/in/en/data/brochure/creta-brochureknight.pdf | https://www.hyundai.com/in/en/blog/hyundai-creta-advance-features-specs-guide
A14: India | B14: Hyundai | C14: Creta | D14: King (automatic: IVT/DCT) | E14: 2026 (current India line-up, Oct 2026) | F14: D4 | G14: ADAS | H14: Lane Departure Warning | I14: U | J14: Unconfirmed – no reliable evidence found | K14: Not listed separately for King.
A15: India | B15: Hyundai | C15: Creta | D15: King (automatic: IVT/DCT) | E15: 2026 (current India line-up, Oct 2026) | F15: D5 | G15: ADAS | H15: Lane Keeping Assist | I15: Y | J15: Present – verified for exact variant | K15: King offers Lane Keeping Assist. | L15: HY-IN-ADV | M15: https://www.hyundai.com/in/en/blog/hyundai-creta-advance-features-specs-guide
A16: India | B16: Hyundai | C16: Creta | D16: King (automatic: IVT/DCT) | E16: 2026 (current India line-up, Oct 2026) | F16: D6 | G16: ADAS | H16: Blind Spot Monitoring | I16: M | J16: Model-level evidence only – exact variant not confirmed | K16: Blind-Spot Collision Avoidance Assist listed in SmartSense suite; trim not stated. | L16: HY-IN-SAFETY | M16: https://www.hyundai.com/in/en/find-a-car/creta/safety
A17: India | B17: Hyundai | C17: Creta | D17: King (automatic: IVT/DCT) | E17: 2026 (current India line-up, Oct 2026) | F17: D7 | G17: ADAS | H17: Rear Cross Traffic Alert | I17: M | J17: Model-level evidence only – exact variant not confirmed | K17: Rear Cross-Traffic Collision Avoidance Assist listed for higher trims; King not named. | L17: HY-IN-SAFETY, HY-IN-PRICE | M17: https://www.hyundai.com/in/en/find-a-car/creta/safety | https://www.hyundai.com/in/en/find-a-car/creta/price
A18: India | B18: Hyundai | C18: Creta | D18: King (automatic: IVT/DCT) | E18: 2026 (current India line-up, Oct 2026) | F18: P1 | G18: Passive safety | H18: Front, side & curtain airbags (6+) | I18: Y | J18: Present – verified for exact variant | K18: Six airbags standard across the line-up. | L18: HY-IN-SAFETY, HY-IN-VAR | M18: https://www.hyundai.com/in/en/find-a-car/creta/safety | https://www.hyundai.com/in/en/blog/hyundai-creta-car-variants-explained
A19: India | B19: Hyundai | C19: Creta | D19: King (automatic: IVT/DCT) | E19: 2026 (current India line-up, Oct 2026) | F19: P2 | G19: Passive safety | H19: Seatbelt pretensioners | I19: Y | J19: Present – verified for exact variant | K19: Seat-belt pretensioners (driver & passenger) listed for all trims. | L19: HY-IN-BROCH | M19: https://www.hyundai.com/content/dam/hyundai/in/en/data/brochure/creta.pdf
A20: India | B20: Hyundai | C20: Creta | D20: King (automatic: IVT/DCT) | E20: 2026 (current India line-up, Oct 2026) | F20: P3 | G20: Passive safety | H20: Seatbelt load limiters | I20: U | J20: Unconfirmed – no reliable evidence found | K20: Load limiter not mentioned.
A21: India | B21: Hyundai | C21: Creta | D21: King (automatic: IVT/DCT) | E21: 2026 (current India line-up, Oct 2026) | F21: P4 | G21: Passive safety | H21: ISOFIX / LATCH child-seat anchors | I21: Y | J21: Present – verified for exact variant | K21: ISOFIX listed for all trims. | L21: HY-IN-BROCH | M21: https://www.hyundai.com/content/dam/hyundai/in/en/data/brochure/creta.pdf
A22: India | B22: Hyundai | C22: Creta | D22: King (automatic: IVT/DCT) | E22: 2026 (current India line-up, Oct 2026) | F22: C1 | G22: Post-crash | H22: Emergency call / SOS (eCall) | I22: M | J22: Model-level evidence only – exact variant not confirmed | K22: Brochure lists an ECM mirror with SOS button; trim fit and auto-crash call not confirmed. | L22: HY-IN-BROCH | M22: https://www.hyundai.com/content/dam/hyundai/in/en/data/brochure/creta.pdf
A23: India | B23: Hyundai | C23: Creta | D23: King (automatic: IVT/DCT) | E23: 2026 (current India line-up, Oct 2026) | F23: C2 | G23: Post-crash | H23: Crash-triggered hazard lights / door unlock | I23: U | J23: Unconfirmed – no reliable evidence found | K23: No official evidence found in this research.
A24: India | B24: Hyundai | C24: Creta | D24: King (automatic: IVT/DCT) | E24: 2026 (current India line-up, Oct 2026) | F24: C3 | G24: Post-crash | H24: Fuel cut-off or high-voltage isolation | I24: U | J24: Unconfirmed – no reliable evidence found | K24: No official evidence found in this research.
A25: India | B25: Hyundai | C25: Creta | D25: King (automatic: IVT/DCT) | E25: 2026 (current India line-up, Oct 2026) | F25: C4 | G25: Post-crash | H25: Event Data Recorder (EDR) | I25: U | J25: Unconfirmed – no reliable evidence found | K25: No official evidence found in this research.
A26: India | B26: Mahindra | C26: XEV 9e | D26: Pack Three | E26: 2025–26 | F26: A1 | G26: Active safety | H26: ABS (anti-lock brakes) | I26: R | J26: Present – required by law in this market | K26: Legal requirement in India since April 2019. | L26: LAW-IN-ABS | M26: https://www.autocarindia.com/car-news/new-cars-and-bikes-to-get-more-safety-tech-this-year-411018
A27: India | B27: Mahindra | C27: XEV 9e | D27: Pack Three | E27: 2025–26 | F27: A2 | G27: Active safety | H27: EBD (brake-force distribution) | I27: U | J27: Unconfirmed – no reliable evidence found | K27: No official evidence found in this research.
A28: India | B28: Mahindra | C28: XEV 9e | D28: Pack Three | E28: 2025–26 | F28: A3 | G28: Active safety | H28: Brake Assist | I28: M | J28: Model-level evidence only – exact variant not confirmed | K28: Owner's manual describes Hydraulic Brake Assist; variant fit not stated. | L28: MA-OM | M28: https://booking.mahindra.com/on/demandware.static/-/Library-Sites-eSUVSharedLibrary/default/dw5ad7dd6c/OwnerManual/XEV_9e_HTML/XEV9e-OM.html
A29: India | B29: Mahindra | C29: XEV 9e | D29: Pack Three | E29: 2025–26 | F29: A4 | G29: Active safety | H29: ESC (stability control) | I29: Y | J29: Present – verified for exact variant | K29: Brochure feature table: ESP standard on Pack Three. | L29: MA-BROCH | M29: https://www.mahindraelectricsuv.com/on/demandware.static/-/Library-Sites-eSUVSharedLibrary/default/MXV9/XEV9e_BROCHURE_R1_20260428.pdf
A30: India | B30: Mahindra | C30: XEV 9e | D30: Pack Three | E30: 2025–26 | F30: A5 | G30: Active safety | H30: Traction control | I30: U | J30: Unconfirmed – no reliable evidence found | K30: No official evidence found in this research.
A31: India | B31: Mahindra | C31: XEV 9e | D31: Pack Three | E31: 2025–26 | F31: A6 | G31: Active safety | H31: TPMS (tyre-pressure monitoring) | I31: Y | J31: Present – verified for exact variant | K31: TPMS with individual tyre display listed for Pack Three. | L31: MA-BROCH, MA-PR-NCAP | M31: https://www.mahindraelectricsuv.com/on/demandware.static/-/Library-Sites-eSUVSharedLibrary/default/MXV9/XEV9e_BROCHURE_R1_20260428.pdf | https://auto.mahindra.com/press-release/xev-nine-e-and-be-six-create-history.html
A32: India | B32: Mahindra | C32: XEV 9e | D32: Pack Three | E32: 2025–26 | F32: A7 | G32: Active safety | H32: Hill Start Assist | I32: M | J32: Model-level evidence only – exact variant not confirmed | K32: Owner's manual describes Hill Hold Control; variant fit not stated. | L32: MA-OM | M32: https://booking.mahindra.com/on/demandware.static/-/Library-Sites-eSUVSharedLibrary/default/dw5ad7dd6c/OwnerManual/XEV_9e_HTML/XEV9e-OM.html
A33: India | B33: Mahindra | C33: XEV 9e | D33: Pack Three | E33: 2025–26 | F33: A8 | G33: Active safety | H33: Hill Descent Control | I33: M | J33: Model-level evidence only – exact variant not confirmed | K33: Owner's manual describes Hill Descent Control; variant fit not stated. | L33: MA-OM | M33: https://booking.mahindra.com/on/demandware.static/-/Library-Sites-eSUVSharedLibrary/default/dw5ad7dd6c/OwnerManual/XEV_9e_HTML/XEV9e-OM.html
A34: India | B34: Mahindra | C34: XEV 9e | D34: Pack Three | E34: 2025–26 | F34: A9 | G34: Active safety | H34: Electric parking brake with Auto Hold | I34: M | J34: Model-level evidence only – exact variant not confirmed | K34: Owner's manual describes EPB with auto vehicle hold; variant fit not stated. | L34: MA-OM | M34: https://booking.mahindra.com/on/demandware.static/-/Library-Sites-eSUVSharedLibrary/default/dw5ad7dd6c/OwnerManual/XEV_9e_HTML/XEV9e-OM.html
A35: India | B35: Mahindra | C35: XEV 9e | D35: Pack Three | E35: 2025–26 | F35: D1 | G35: ADAS | H35: Forward Collision Warning | I35: Y | J35: Present – verified for exact variant | K35: Pack Three Level 2+ ADAS (5 radars + camera) includes front collision warning. | L35: MA-PR-TOP, MA-BROCH | M35: https://auto.mahindra.com/press-release/mahindra-democratises-premium-ev-technology-announces-top-variant-prices-of-be-6-and-xev-9e.html | https://www.mahindraelectricsuv.com/on/demandware.static/-/Library-Sites-eSUVSharedLibrary/default/MXV9/XEV9e_BROCHURE_R1_20260428.pdf
A36: India | B36: Mahindra | C36: XEV 9e | D36: Pack Three | E36: 2025–26 | F36: D2 | G36: ADAS | H36: Automatic Emergency Braking | I36: Y | J36: Present – verified for exact variant | K36: Pack Three Level 2+ ADAS includes automatic emergency braking. | L36: MA-PR-TOP, MA-BROCH | M36: https://auto.mahindra.com/press-release/mahindra-democratises-premium-ev-technology-announces-top-variant-prices-of-be-6-and-xev-9e.html | https://www.mahindraelectricsuv.com/on/demandware.static/-/Library-Sites-eSUVSharedLibrary/default/MXV9/XEV9e_BROCHURE_R1_20260428.pdf
A37: India | B37: Mahindra | C37: XEV 9e | D37: Pack Three | E37: 2025–26 | F37: D3 | G37: ADAS | H37: Adaptive Cruise Control | I37: M | J37: Model-level evidence only – exact variant not confirmed | K37: ACC with stop-and-go confirmed for the Cineluxe Edition only. | L37: MA-FAQ | M37: https://www.mahindraelectricsuv.com/faq.html
A38: India | B38: Mahindra | C38: XEV 9e | D38: Pack Three | E38: 2025–26 | F38: D4 | G38: ADAS | H38: Lane Departure Warning | I38: U | J38: Unconfirmed – no reliable evidence found | K38: No official evidence found in this research.
A39: India | B39: Mahindra | C39: XEV 9e | D39: Pack Three | E39: 2025–26 | F39: D5 | G39: ADAS | H39: Lane Keeping Assist | I39: Y | J39: Present – verified for exact variant | K39: Lane centring listed in Pack Three Level 2+ suite (counted as lane keeping support). | L39: MA-PR-TOP | M39: https://auto.mahindra.com/press-release/mahindra-democratises-premium-ev-technology-announces-top-variant-prices-of-be-6-and-xev-9e.html
A40: India | B40: Mahindra | C40: XEV 9e | D40: Pack Three | E40: 2025–26 | F40: D6 | G40: ADAS | H40: Blind Spot Monitoring | I40: Y | J40: Present – verified for exact variant | K40: Blind spot detection listed in Pack Three Level 2+ suite. | L40: MA-PR-TOP, MA-PR-NCAP | M40: https://auto.mahindra.com/press-release/mahindra-democratises-premium-ev-technology-announces-top-variant-prices-of-be-6-and-xev-9e.html | https://auto.mahindra.com/press-release/xev-nine-e-and-be-six-create-history.html
A41: India | B41: Mahindra | C41: XEV 9e | D41: Pack Three | E41: 2025–26 | F41: D7 | G41: ADAS | H41: Rear Cross Traffic Alert | I41: Y | J41: Present – verified for exact variant | K41: Rear cross traffic alert listed in the Pack Three column and press release. | L41: MA-BROCH, MA-PR-TOP | M41: https://www.mahindraelectricsuv.com/on/demandware.static/-/Library-Sites-eSUVSharedLibrary/default/MXV9/XEV9e_BROCHURE_R1_20260428.pdf | https://auto.mahindra.com/press-release/mahindra-democratises-premium-ev-technology-announces-top-variant-prices-of-be-6-and-xev-9e.html
A42: India | B42: Mahindra | C42: XEV 9e | D42: Pack Three | E42: 2025–26 | F42: P1 | G42: Passive safety | H42: Front, side & curtain airbags (6+) | I42: Y | J42: Present – verified for exact variant | K42: Seven airbags. | L42: MA-PR-NCAP, MA-BROCH | M42: https://auto.mahindra.com/press-release/xev-nine-e-and-be-six-create-history.html | https://www.mahindraelectricsuv.com/on/demandware.static/-/Library-Sites-eSUVSharedLibrary/default/MXV9/XEV9e_BROCHURE_R1_20260428.pdf
A43: India | B43: Mahindra | C43: XEV 9e | D43: Pack Three | E43: 2025–26 | F43: P2 | G43: Passive safety | H43: Seatbelt pretensioners | I43: M | J43: Model-level evidence only – exact variant not confirmed | K43: Owner's manual describes belt pretensioners; variant fit not stated. | L43: MA-OM | M43: https://booking.mahindra.com/on/demandware.static/-/Library-Sites-eSUVSharedLibrary/default/dw5ad7dd6c/OwnerManual/XEV_9e_HTML/XEV9e-OM.html
A44: India | B44: Mahindra | C44: XEV 9e | D44: Pack Three | E44: 2025–26 | F44: P3 | G44: Passive safety | H44: Seatbelt load limiters | I44: U | J44: Unconfirmed – no reliable evidence found | K44: No official evidence found in this research.
A45: India | B45: Mahindra | C45: XEV 9e | D45: Pack Three | E45: 2025–26 | F45: P4 | G45: Passive safety | H45: ISOFIX / LATCH child-seat anchors | I45: Y | J45: Present – verified for exact variant | K45: ISOFIX rear seats standard on Pack Three. | L45: MA-BROCH | M45: https://www.mahindraelectricsuv.com/on/demandware.static/-/Library-Sites-eSUVSharedLibrary/default/MXV9/XEV9e_BROCHURE_R1_20260428.pdf
A46: India | B46: Mahindra | C46: XEV 9e | D46: Pack Three | E46: 2025–26 | F46: C1 | G46: Post-crash | H46: Emergency call / SOS (eCall) | I46: M | J46: Model-level evidence only – exact variant not confirmed | K46: Owner's manual: automatic call to 108 after airbag deployment + manual SOS; variant fit not stated. | L46: MA-OM | M46: https://booking.mahindra.com/on/demandware.static/-/Library-Sites-eSUVSharedLibrary/default/dw5ad7dd6c/OwnerManual/XEV_9e_HTML/XEV9e-OM.html
A47: India | B47: Mahindra | C47: XEV 9e | D47: Pack Three | E47: 2025–26 | F47: C2 | G47: Post-crash | H47: Crash-triggered hazard lights / door unlock | I47: U | J47: Unconfirmed – no reliable evidence found | K47: No official evidence found in this research.
A48: India | B48: Mahindra | C48: XEV 9e | D48: Pack Three | E48: 2025–26 | F48: C3 | G48: Post-crash | H48: Fuel cut-off or high-voltage isolation | I48: U | J48: Unconfirmed – no reliable evidence found | K48: No official evidence found in this research.
A49: India | B49: Mahindra | C49: XEV 9e | D49: Pack Three | E49: 2025–26 | F49: C4 | G49: Post-crash | H49: Event Data Recorder (EDR) | I49: U | J49: Unconfirmed – no reliable evidence found | K49: No official evidence found in this research.
A50: India | B50: Škoda | C50: Kylaq | D50: Prestige+ (top variant) | E50: 2025–26 | F50: A1 | G50: Active safety | H50: ABS (anti-lock brakes) | I50: Y | J50: Present – verified for exact variant | K50: ABS standard on all variants (25 standard safety features). | L50: SK-PR, SK-SAFETY | M50: https://www.skoda-storyboard.com/en/press-releases/the-all-new-skoda-kylaq-a-new-era-for-skoda-in-indias-popular-sub-4-metre-suv-segment/ | https://www.skoda-auto.co.in/shopping/kylaq-safety
A51: India | B51: Škoda | C51: Kylaq | D51: Prestige+ (top variant) | E51: 2025–26 | F51: A2 | G51: Active safety | H51: EBD (brake-force distribution) | I51: Y | J51: Present – verified for exact variant | K51: EBD standard on all variants. | L51: SK-PR | M51: https://www.skoda-storyboard.com/en/press-releases/the-all-new-skoda-kylaq-a-new-era-for-skoda-in-indias-popular-sub-4-metre-suv-segment/
A52: India | B52: Škoda | C52: Kylaq | D52: Prestige+ (top variant) | E52: 2025–26 | F52: A3 | G52: Active safety | H52: Brake Assist | I52: U | J52: Unconfirmed – no reliable evidence found | K52: Brake assist not named.
A53: India | B53: Škoda | C53: Kylaq | D53: Prestige+ (top variant) | E53: 2025–26 | F53: A4 | G53: Active safety | H53: ESC (stability control) | I53: Y | J53: Present – verified for exact variant | K53: ESC standard on all variants. | L53: SK-PR, SK-SAFETY | M53: https://www.skoda-storyboard.com/en/press-releases/the-all-new-skoda-kylaq-a-new-era-for-skoda-in-indias-popular-sub-4-metre-suv-segment/ | https://www.skoda-auto.co.in/shopping/kylaq-safety
A54: India | B54: Škoda | C54: Kylaq | D54: Prestige+ (top variant) | E54: 2025–26 | F54: A5 | G54: Active safety | H54: Traction control | I54: M | J54: Model-level evidence only – exact variant not confirmed | K54: TCS listed in the older Prestige brochure; Prestige+ fit not confirmed. | L54: SK-BROCH | M54: https://www.skoda-auto.co.in/_doc/54fc9665-9adc-4e0e-97ae-0a6b798d59c2
A55: India | B55: Škoda | C55: Kylaq | D55: Prestige+ (top variant) | E55: 2025–26 | F55: A6 | G55: Active safety | H55: TPMS (tyre-pressure monitoring) | I55: M | J55: Model-level evidence only – exact variant not confirmed | K55: TPMS on 'select variants'; Prestige+ not named. | L55: SK-PR, SK-SAFETY | M55: https://www.skoda-storyboard.com/en/press-releases/the-all-new-skoda-kylaq-a-new-era-for-skoda-in-indias-popular-sub-4-metre-suv-segment/ | https://www.skoda-auto.co.in/shopping/kylaq-safety
A56: India | B56: Škoda | C56: Kylaq | D56: Prestige+ (top variant) | E56: 2025–26 | F56: A7 | G56: Active safety | H56: Hill Start Assist | I56: M | J56: Model-level evidence only – exact variant not confirmed | K56: Sources conflict: Hill Hold standard vs 'select variants'. | L56: SK-PR, SK-SAFETY | M56: https://www.skoda-storyboard.com/en/press-releases/the-all-new-skoda-kylaq-a-new-era-for-skoda-in-indias-popular-sub-4-metre-suv-segment/ | https://www.skoda-auto.co.in/shopping/kylaq-safety
A57: India | B57: Škoda | C57: Kylaq | D57: Prestige+ (top variant) | E57: 2025–26 | F57: A8 | G57: Active safety | H57: Hill Descent Control | I57: U | J57: Unconfirmed – no reliable evidence found | K57: No official evidence found in this research.
A58: India | B58: Škoda | C58: Kylaq | D58: Prestige+ (top variant) | E58: 2025–26 | F58: A9 | G58: Active safety | H58: Electric parking brake with Auto Hold | I58: U | J58: Unconfirmed – no reliable evidence found | K58: No official evidence found in this research.
A59: India | B59: Škoda | C59: Kylaq | D59: Prestige+ (top variant) | E59: 2025–26 | F59: D1 | G59: ADAS | H59: Forward Collision Warning | I59: U | J59: Unconfirmed – no reliable evidence found | K59: No official evidence found in this research.
A60: India | B60: Škoda | C60: Kylaq | D60: Prestige+ (top variant) | E60: 2025–26 | F60: D2 | G60: ADAS | H60: Automatic Emergency Braking | I60: U | J60: Unconfirmed – no reliable evidence found | K60: No official evidence found in this research.
A61: India | B61: Škoda | C61: Kylaq | D61: Prestige+ (top variant) | E61: 2025–26 | F61: D3 | G61: ADAS | H61: Adaptive Cruise Control | I61: U | J61: Unconfirmed – no reliable evidence found | K61: No official evidence found in this research.
A62: India | B62: Škoda | C62: Kylaq | D62: Prestige+ (top variant) | E62: 2025–26 | F62: D4 | G62: ADAS | H62: Lane Departure Warning | I62: U | J62: Unconfirmed – no reliable evidence found | K62: No official evidence found in this research.
A63: India | B63: Škoda | C63: Kylaq | D63: Prestige+ (top variant) | E63: 2025–26 | F63: D5 | G63: ADAS | H63: Lane Keeping Assist | I63: U | J63: Unconfirmed – no reliable evidence found | K63: No official evidence found in this research.
A64: India | B64: Škoda | C64: Kylaq | D64: Prestige+ (top variant) | E64: 2025–26 | F64: D6 | G64: ADAS | H64: Blind Spot Monitoring | I64: U | J64: Unconfirmed – no reliable evidence found | K64: No official evidence found in this research.
A65: India | B65: Škoda | C65: Kylaq | D65: Prestige+ (top variant) | E65: 2025–26 | F65: D7 | G65: ADAS | H65: Rear Cross Traffic Alert | I65: U | J65: Unconfirmed – no reliable evidence found | K65: No official evidence found in this research.
A66: India | B66: Škoda | C66: Kylaq | D66: Prestige+ (top variant) | E66: 2025–26 | F66: P1 | G66: Passive safety | H66: Front, side & curtain airbags (6+) | I66: Y | J66: Present – verified for exact variant | K66: Six airbags standard on every Kylaq. | L66: SK-PR, SK-50K | M66: https://www.skoda-storyboard.com/en/press-releases/the-all-new-skoda-kylaq-a-new-era-for-skoda-in-indias-popular-sub-4-metre-suv-segment/ | https://www.skoda-auto.co.in/news/news-detail/skoda-kylaq-marks-one-year-landmark-by-celebrating-50k-sales-milestone
A67: India | B67: Škoda | C67: Kylaq | D67: Prestige+ (top variant) | E67: 2025–26 | F67: P2 | G67: Passive safety | H67: Seatbelt pretensioners | I67: U | J67: Unconfirmed – no reliable evidence found | K67: No official evidence found in this research.
A68: India | B68: Škoda | C68: Kylaq | D68: Prestige+ (top variant) | E68: 2025–26 | F68: P3 | G68: Passive safety | H68: Seatbelt load limiters | I68: U | J68: Unconfirmed – no reliable evidence found | K68: No official evidence found in this research.
A69: India | B69: Škoda | C69: Kylaq | D69: Prestige+ (top variant) | E69: 2025–26 | F69: P4 | G69: Passive safety | H69: ISOFIX / LATCH child-seat anchors | I69: Y | J69: Present – verified for exact variant | K69: ISOFIX standard. | L69: SK-PR, SK-SAFETY | M69: https://www.skoda-storyboard.com/en/press-releases/the-all-new-skoda-kylaq-a-new-era-for-skoda-in-indias-popular-sub-4-metre-suv-segment/ | https://www.skoda-auto.co.in/shopping/kylaq-safety
A70: India | B70: Škoda | C70: Kylaq | D70: Prestige+ (top variant) | E70: 2025–26 | F70: C1 | G70: Post-crash | H70: Emergency call / SOS (eCall) | I70: U | J70: Unconfirmed – no reliable evidence found | K70: No official evidence found in this research.
A71: India | B71: Škoda | C71: Kylaq | D71: Prestige+ (top variant) | E71: 2025–26 | F71: C2 | G71: Post-crash | H71: Crash-triggered hazard lights / door unlock | I71: U | J71: Unconfirmed – no reliable evidence found | K71: No official evidence found in this research.
A72: India | B72: Škoda | C72: Kylaq | D72: Prestige+ (top variant) | E72: 2025–26 | F72: C3 | G72: Post-crash | H72: Fuel cut-off or high-voltage isolation | I72: U | J72: Unconfirmed – no reliable evidence found | K72: No official evidence found in this research.
A73: India | B73: Škoda | C73: Kylaq | D73: Prestige+ (top variant) | E73: 2025–26 | F73: C4 | G73: Post-crash | H73: Event Data Recorder (EDR) | I73: U | J73: Unconfirmed – no reliable evidence found | K73: No official evidence found in this research.
A74: India | B74: Maruti Suzuki | C74: Swift | D74: ZXi+ | E74: 2024– (4th generation) | F74: A1 | G74: Active safety | H74: ABS (anti-lock brakes) | I74: Y | J74: Present – verified for exact variant | K74: ABS with EBD standard (launch release). | L74: MS-SWIFT-PR, MS-SWIFT | M74: https://www.marutisuzuki.com/corporate/media/press-releases/2024/may/ms-launches-epic-new-swift-with-all-new-z-series-engine | https://www.marutisuzuki.com/arena/swift
A75: India | B75: Maruti Suzuki | C75: Swift | D75: ZXi+ | E75: 2024– (4th generation) | F75: A2 | G75: Active safety | H75: EBD (brake-force distribution) | I75: Y | J75: Present – verified for exact variant | K75: EBD standard. | L75: MS-SWIFT-PR | M75: https://www.marutisuzuki.com/corporate/media/press-releases/2024/may/ms-launches-epic-new-swift-with-all-new-z-series-engine
A76: India | B76: Maruti Suzuki | C76: Swift | D76: ZXi+ | E76: 2024– (4th generation) | F76: A3 | G76: Active safety | H76: Brake Assist | I76: Y | J76: Present – verified for exact variant | K76: Brake Assist standard. | L76: MS-SWIFT-PR | M76: https://www.marutisuzuki.com/corporate/media/press-releases/2024/may/ms-launches-epic-new-swift-with-all-new-z-series-engine
A77: India | B77: Maruti Suzuki | C77: Swift | D77: ZXi+ | E77: 2024– (4th generation) | F77: A4 | G77: Active safety | H77: ESC (stability control) | I77: Y | J77: Present – verified for exact variant | K77: ESP standard. | L77: MS-SWIFT, MS-SWIFT-PR | M77: https://www.marutisuzuki.com/arena/swift | https://www.marutisuzuki.com/corporate/media/press-releases/2024/may/ms-launches-epic-new-swift-with-all-new-z-series-engine
A78: India | B78: Maruti Suzuki | C78: Swift | D78: ZXi+ | E78: 2024– (4th generation) | F78: A5 | G78: Active safety | H78: Traction control | I78: U | J78: Unconfirmed – no reliable evidence found | K78: No official evidence found in this research.
A79: India | B79: Maruti Suzuki | C79: Swift | D79: ZXi+ | E79: 2024– (4th generation) | F79: A6 | G79: Active safety | H79: TPMS (tyre-pressure monitoring) | I79: U | J79: Unconfirmed – no reliable evidence found | K79: No official evidence found in this research.
A80: India | B80: Maruti Suzuki | C80: Swift | D80: ZXi+ | E80: 2024– (4th generation) | F80: A7 | G80: Active safety | H80: Hill Start Assist | I80: Y | J80: Present – verified for exact variant | K80: Hill Hold Assist listed for ZXi+. | L80: MS-SWIFT, MS-SWIFT-VAR | M80: https://www.marutisuzuki.com/arena/swift | https://marutisuzuki.com/cng/swift
A81: India | B81: Maruti Suzuki | C81: Swift | D81: ZXi+ | E81: 2024– (4th generation) | F81: A8 | G81: Active safety | H81: Hill Descent Control | I81: U | J81: Unconfirmed – no reliable evidence found | K81: No official evidence found in this research.
A82: India | B82: Maruti Suzuki | C82: Swift | D82: ZXi+ | E82: 2024– (4th generation) | F82: A9 | G82: Active safety | H82: Electric parking brake with Auto Hold | I82: U | J82: Unconfirmed – no reliable evidence found | K82: No official evidence found in this research.
A83: India | B83: Maruti Suzuki | C83: Swift | D83: ZXi+ | E83: 2024– (4th generation) | F83: D1 | G83: ADAS | H83: Forward Collision Warning | I83: U | J83: Unconfirmed – no reliable evidence found | K83: No official evidence found in this research.
A84: India | B84: Maruti Suzuki | C84: Swift | D84: ZXi+ | E84: 2024– (4th generation) | F84: D2 | G84: ADAS | H84: Automatic Emergency Braking | I84: U | J84: Unconfirmed – no reliable evidence found | K84: No official evidence found in this research.
A85: India | B85: Maruti Suzuki | C85: Swift | D85: ZXi+ | E85: 2024– (4th generation) | F85: D3 | G85: ADAS | H85: Adaptive Cruise Control | I85: U | J85: Unconfirmed – no reliable evidence found | K85: No official evidence found in this research.
A86: India | B86: Maruti Suzuki | C86: Swift | D86: ZXi+ | E86: 2024– (4th generation) | F86: D4 | G86: ADAS | H86: Lane Departure Warning | I86: U | J86: Unconfirmed – no reliable evidence found | K86: No official evidence found in this research.
A87: India | B87: Maruti Suzuki | C87: Swift | D87: ZXi+ | E87: 2024– (4th generation) | F87: D5 | G87: ADAS | H87: Lane Keeping Assist | I87: U | J87: Unconfirmed – no reliable evidence found | K87: No official evidence found in this research.
A88: India | B88: Maruti Suzuki | C88: Swift | D88: ZXi+ | E88: 2024– (4th generation) | F88: D6 | G88: ADAS | H88: Blind Spot Monitoring | I88: U | J88: Unconfirmed – no reliable evidence found | K88: No official evidence found in this research.
A89: India | B89: Maruti Suzuki | C89: Swift | D89: ZXi+ | E89: 2024– (4th generation) | F89: D7 | G89: ADAS | H89: Rear Cross Traffic Alert | I89: U | J89: Unconfirmed – no reliable evidence found | K89: No official evidence found in this research.
A90: India | B90: Maruti Suzuki | C90: Swift | D90: ZXi+ | E90: 2024– (4th generation) | F90: P1 | G90: Passive safety | H90: Front, side & curtain airbags (6+) | I90: Y | J90: Present – verified for exact variant | K90: Six airbags standard across all variants. | L90: MS-SWIFT | M90: https://www.marutisuzuki.com/arena/swift
A91: India | B91: Maruti Suzuki | C91: Swift | D91: ZXi+ | E91: 2024– (4th generation) | F91: P2 | G91: Passive safety | H91: Seatbelt pretensioners | I91: Y | J91: Present – verified for exact variant | K91: ZXi+ listing: front seat belts with pre-tensioner. | L91: MS-SWIFT-VAR | M91: https://marutisuzuki.com/cng/swift
A92: India | B92: Maruti Suzuki | C92: Swift | D92: ZXi+ | E92: 2024– (4th generation) | F92: P3 | G92: Passive safety | H92: Seatbelt load limiters | I92: Y | J92: Present – verified for exact variant | K92: ZXi+ listing: front seat belts with force (load) limiter. | L92: MS-SWIFT-VAR | M92: https://marutisuzuki.com/cng/swift
A93: India | B93: Maruti Suzuki | C93: Swift | D93: ZXi+ | E93: 2024– (4th generation) | F93: P4 | G93: Passive safety | H93: ISOFIX / LATCH child-seat anchors | I93: Y | J93: Present – verified for exact variant | K93: ISOFIX child seat anchorages listed for ZXi+. | L93: MS-SWIFT-VAR | M93: https://marutisuzuki.com/cng/swift
A94: India | B94: Maruti Suzuki | C94: Swift | D94: ZXi+ | E94: 2024– (4th generation) | F94: C1 | G94: Post-crash | H94: Emergency call / SOS (eCall) | I94: U | J94: Unconfirmed – no reliable evidence found | K94: No official evidence found in this research.
A95: India | B95: Maruti Suzuki | C95: Swift | D95: ZXi+ | E95: 2024– (4th generation) | F95: C2 | G95: Post-crash | H95: Crash-triggered hazard lights / door unlock | I95: U | J95: Unconfirmed – no reliable evidence found | K95: No official evidence found in this research.
A96: India | B96: Maruti Suzuki | C96: Swift | D96: ZXi+ | E96: 2024– (4th generation) | F96: C3 | G96: Post-crash | H96: Fuel cut-off or high-voltage isolation | I96: U | J96: Unconfirmed – no reliable evidence found | K96: No official evidence found in this research.
A97: India | B97: Maruti Suzuki | C97: Swift | D97: ZXi+ | E97: 2024– (4th generation) | F97: C4 | G97: Post-crash | H97: Event Data Recorder (EDR) | I97: U | J97: Unconfirmed – no reliable evidence found | K97: No official evidence found in this research.
A98: India | B98: Maruti Suzuki | C98: Alto K10 | D98: Any variant (features stated standard on all variants) | E98: 2025–26 | F98: A1 | G98: Active safety | H98: ABS (anti-lock brakes) | I98: Y | J98: Present – verified for exact variant | K98: ABS with EBD listed as existing standard safety. | L98: MS-ALTO-6AB | M98: https://www.marutisuzuki.com/corporate/media/press-releases/2025/may/maruti-suzuki-arena-enhances-safety-by-offering-6-airbags-as-standard
A99: India | B99: Maruti Suzuki | C99: Alto K10 | D99: Any variant (features stated standard on all variants) | E99: 2025–26 | F99: A2 | G99: Active safety | H99: EBD (brake-force distribution) | I99: Y | J99: Present – verified for exact variant | K99: EBD listed with ABS. | L99: MS-ALTO-6AB | M99: https://www.marutisuzuki.com/corporate/media/press-releases/2025/may/maruti-suzuki-arena-enhances-safety-by-offering-6-airbags-as-standard
A100: India | B100: Maruti Suzuki | C100: Alto K10 | D100: Any variant (features stated standard on all variants) | E100: 2025–26 | F100: A3 | G100: Active safety | H100: Brake Assist | I100: U | J100: Unconfirmed – no reliable evidence found | K100: No official evidence found in this research.
...

Sheet Band Summary
A1: Band | B1: Rule (verified coverage) | C1: Vehicles in band | D1: Examples (exact variant, verified score)
A2: 100% – Complete | B2: =100% -> 1 | C2: =COUNTIF('Coverage Matrix'!$AJ$2:$AJ$10,">=1") -> 0 | D2: No vehicle in the reviewed sample could be confirmed to include every feature in the defined checklist.
A3: 75% band | B3: 75% to 99.9% | C3: =COUNTIFS('Coverage Matrix'!$AJ$2:$AJ$10,">=0.75",'Coverage Matrix'!$AJ$2:$AJ$10,"<1") -> 0 | D3: No vehicle in the reviewed sample reached 75% on verified evidence.
A4: 50% band | B4: 50% to 74.9% | C4: =COUNTIFS('Coverage Matrix'!$AJ$2:$AJ$10,">=0.5",'Coverage Matrix'!$AJ$2:$AJ$10,"<0.75") -> 2 | D4: Hyundai IONIQ 5 N IONIQ 5 N (single trim) (United States, MY2026): 13/24 = 54.2%; Hyundai Creta King (automatic: IVT/DCT) (India, 2026 (current India line-up, Oct 2026)): 12/24 = 50.0%
A5: 25% band | B5: 25% to 49.9% | C5: =COUNTIFS('Coverage Matrix'!$AJ$2:$AJ$10,">=0.25",'Coverage Matrix'!$AJ$2:$AJ$10,"<0.5") -> 4 | D5: Dacia Sandero Essential (entry trim) (United Kingdom, 2025–26 (GSR2-compliant)): 11/24 = 45.8%; Mahindra XEV 9e Pack Three (India, 2025–26): 10/24 = 41.7%; Maruti Suzuki Swift ZXi+ (India, 2024– (4th generation)): 9/24 = 37.5%; Tesla Model Y Premium (Long Range) (United States, 2025+ (MY2026, software 2026.32)): 6/24 = 25.0%
A6: Below 25% | B6: under 25% | C6: =COUNTIF('Coverage Matrix'!$AJ$2:$AJ$10,"<0.25") -> 3 | D6: Škoda Kylaq Prestige+ (top variant) (India, 2025–26): 5/24 = 20.8%; Volvo XC90 T8 plug-in hybrid, Core grade (United Kingdom, MY2025 (updated XC90)): 5/24 = 20.8%; Maruti Suzuki Alto K10 Any variant (features stated standard on all variants) (India, 2025–26): 4/24 = 16.7%
A8: Counts are live formulas on the 'Coverage Matrix' sheet; the example text was written at the research date and does not update automatically.

Sheet Source Register
A1: Source ID | B1: Publisher | C1: Title / description | D1: URL | E1: Source type | F1: Used for (vehicles / topics)
A2: LAW-IN-ABS | B2: Autocar India (cited in original deck) | C2: ABS compulsory on all cars on sale in India from April 2019 | D2: https://www.autocarindia.com/car-news/new-cars-and-bikes-to-get-more-safety-tech-this-year-411018 | E2: Regulatory (secondary report) | F2: Hyundai Creta; Mahindra XEV 9e
A3: LAW-US-126 | B3: NHTSA | C3: FMVSS No. 126 Electronic Stability Control Systems | D3: https://www.nhtsa.gov/document/electronic-stability-control-systems-fmvss-no-126 | E3: Regulation | F3: Hyundai IONIQ 5 N; Tesla Model Y
A4: LAW-US-138 | B4: NHTSA | C4: FMVSS No. 138 Tire Pressure Monitoring Systems | D4: https://www.nhtsa.gov/sites/nhtsa.gov/files/fmvss/tirepressure-fmvss-138.pdf | E4: Regulation | F4: Hyundai IONIQ 5 N; Tesla Model Y
A5: LAW-US-127 | B5: NHTSA | C5: FMVSS No. 127 Automatic Emergency Braking final rule (compliance from 1 Sept 2029) | D5: https://www.nhtsa.gov/press-releases/nhtsa-fmvss-127-automatic-emergency-braking-reduce-crashes | E5: Regulation | F5: India vs global slide
A6: LAW-EU-GSR2 | B6: EUR-Lex | C6: Regulation (EU) 2019/2144 consolidated text (07.07.2024) | D6: https://eur-lex.europa.eu/eli/reg/2019/2144/2024-07-07/eng | E6: Regulation | F6: India vs global slide; crash sequence slide
A7: LAW-EU-GSR2-PR | B7: European Commission | C7: Mandatory driver assistance systems apply to all new vehicles from 7 July 2024 | D7: https://single-market-economy.ec.europa.eu/news/mandatory-drivers-assistance-systems-expected-help-save-over-25000-lives-2038-2024-07-05_en | E7: Regulation | F7: India vs global slide
A8: LAW-EU-ECALL | B8: European Union – Your Europe (cited in original deck) | C8: eCall in new car models approved after 31 March 2018 | D8: https://europa.eu/youreurope/citizens/travel/security-and-emergencies/emergency-assistance-vehicles-ecall/index_en.htm | E8: Regulation | F8: India vs global slide; crash sequence slide
A9: BNCAP | B9: PIB, Government of India | C9: Bharat NCAP launched 22 Aug 2023; testing from 1 Oct 2023 | D9: https://www.pib.gov.in/PressReleaseIframePage.aspx?PRID=1951030&reg=3&lang=2 | E9: Regulatory / testing | F9: India vs global slide
A10: BNCAP-FAQ | B10: Bharat NCAP | C10: Programme website (voluntary star rating) | D10: https://www.bncap.in/ | E10: Testing organisation | F10: India vs global slide
A11: HY-IN-SAFETY | B11: Hyundai Motor India | C11: CRETA safety page | D11: https://www.hyundai.com/in/en/find-a-car/creta/safety | E11: Official model page | F11: Hyundai Creta
A12: HY-IN-FEAT | B12: Hyundai Motor India | C12: CRETA features page (variant feature table) | D12: https://www.hyundai.com/in/en/find-a-car/creta/features | E12: Official model page | F12: Hyundai Creta
... A53: DA-PAGE | B53: Dacia UK | C53: New Sandero model page | D53: https://www.dacia.co.uk/vehicles/sandero.html | E53: Official model page | F53: Dacia Sandero
